Workbook

Sheet Tab1_Drivers
A1: Tab 1 — Operational Drivers & Volume
A2: Visa Inc. · $ in millions unless noted · FY ends Sep 30 · green = link · black = formula · blue on yellow = base-case assumption
B3: Historical (audited) | G3: Projections — base case
A4: Line item | B4: FY21 | C4: FY22 | D4: FY23 | E4: FY24 | F4: FY25 | G4: FY26P | H4: FY27P | I4: FY28P | J4: FY29P | K4: FY30P | L4: Formula / note
A6: Payment volume & transactions
A7: Payments volume ($ billions) | B7: =Data!C8 -> 10400 | C7: =Data!D8 -> 11600 | D7: =Data!E8 -> 12300 | E7: =Data!F8 -> 13200 | F7: =Data!G8 -> 14200 | G7: =F7*(1+G8) -> 15620 | H7: =G7*(1+H8) -> 16869.6 | I7: =H7*(1+I8) -> 18219.168 | J7: =I7*(1+J8) -> 19585.606 | K7: =J7*(1+K8) -> 20956.598 | L7: Hist: Data tab · Proj: prior year × (1 + growth)
A8: YoY growth | C8: =C7/B7-1 -> 0.11538462 | D8: =D7/C7-1 -> 0.060344828 | E8: =E7/D7-1 -> 0.073170732 | F8: =F7/E7-1 -> 0.075757576 | G8: 0.1 | H8: 0.08 | I8: 0.08 | J8: 0.075 | K8: 0.07 | L8: FY26P 10%: Q3 FY26 payments volume +11% nominal / +10% constant $; then fades to ~7% (FY22–25 avg ~7%)
A9: Processed transactions (billions) | B9: =Data!C9 -> 164.7 | C9: =Data!D9 -> 192.5 | D9: =Data!E9 -> 212.6 | E9: =Data!F9 -> 233.8 | F9: =Data!G9 -> 257.5 | G9: =F9*(1+G10) -> 283.25 | H9: =G9*(1+H10) -> 308.7425 | I9: =H9*(1+I10) -> 336.52932 | J9: =I9*(1+J10) -> 363.45167 | K9: =J9*(1+K10) -> 392.5278 | L9: Hist: Data tab · Proj: prior year × (1 + growth)
A10: YoY growth | C10: =C9/B9-1 -> 0.16879174 | D10: =D9/C9-1 -> 0.10441558 | E10: =E9/D9-1 -> 0.09971778 | F10: =F9/E9-1 -> 0.10136869 | G10: 0.1 | H10: 0.09 | I10: 0.09 | J10: 0.08 | K10: 0.08 | L10: FY26P 10%: Q3 FY26 processed transactions +10%; FY23–25 ran ~10%
A11: Average transaction size ($) | B11: =B7/B9 -> 63.145112 | C11: =C7/C9 -> 60.25974 | D11: =D7/D9 -> 57.855127 | E11: =E7/E9 -> 56.458512 | F11: =F7/F9 -> 55.145631 | G11: =G7/G9 -> 55.145631 | H11: =H7/H9 -> 54.639708 | I11: =I7/I9 -> 54.138426 | ... K11: =K7/K9 -> 53.388824 | L11: Formula: Payments volume / Processed transactions · proxy only, see note 2
A12: YoY growth | C12: =C11/B11-1 -> -0.045694306 | D12: =D11/C11-1 -> -0.039904142 | E12: =E11/D11-1 -> -0.024139874 | F12: =F11/E11-1 -> -0.023253898 | G12: =G11/F11-1 -> 0 | H12: =H11/G11-1 -> -0.0091743119 | I12: =I11/H11-1 -> -0.0091743119 | J12: =J11/I11-1 -> -0.0046296296 | K12: =K11/J11-1 -> -0.0092592593
A14: Revenue breakdown ($ millions)
A15: Service revenues | B15: =Data!C12 -> 11475 | C15: =Data!D12 -> 13361 | D15: =Data!E12 -> 14826 | E15: =Data!F12 -> 16114 | F15: =Data!G12 -> 17539 | G15: =G39/10000*G7*1000 -> 19837.4 | H15: =H39/10000*H7*1000 -> 21593.088 | I15: =I39/10000*I7*1000 -> 23502.727 | J15: =J39/10000*J7*1000 -> 25461.287 | K15: =K39/10000*K7*1000 -> 27453.143 | L15: Proj: Payments volume × service yield (see efficiency block)
A16: Data processing revenues | B16: =Data!C13 -> 12792 | C16: =Data!D13 -> 14438 | D16: =Data!E13 -> 16007 | E16: =Data!F13 -> 17714 | F16: =Data!G13 -> 19993 | G16: =G40*G9*1000 -> 23226.5 | H16: =H40*H9*1000 -> 25625.627 | I16: =I40*I9*1000 -> 28268.463 | J16: =J40*J9*1000 -> 30893.392 | K16: =K40*K9*1000 -> 33757.391 | L16: Proj: Processed transactions × DP revenue per transaction
A17: International transaction revenues | B17: =Data!C14 -> 6530 | C17: =Data!D14 -> 9815 | D17: =Data!E14 -> 11638 | E17: =Data!F14 -> 12665 | F17: =Data!G14 -> 14166 | G17: =F17*(1+G18) -> 15299.28 | H17: =G17*(1+H18) -> 16829.208 | I17: =H17*(1+I18) -> 18512.129 | J17: =I17*(1+J18) -> 20178.22 | K17: =J17*(1+K18) -> 21994.26 | L17: Proj: prior year × (1 + growth) · driven by cross-border volume
A18: YoY growth | C18: =C17/B17-1 -> 0.50306279 | D18: =D17/C17-1 -> 0.18573612 | E18: =E17/D17-1 -> 0.088245403 | F18: =F17/E17-1 -> 0.11851559 | G18: 0.08 | H18: 0.1 | I18: 0.1 | J18: 0.09 | K18: 0.09 | L18: FY26P 8%: Q3 FY26 +6% despite cross-border volume +13–15% (pricing/FX mix); normalises to ~9–10%
A19: Other revenues | B19: =Data!C15 -> 1675 | C19: =Data!D15 -> 1991 | D19: =Data!E15 -> 2479 | E19: =Data!F15 -> 3197 | F19: =Data!G15 -> 4053 | G19: =F19*(1+G20) -> 5674.2 | H19: =G19*(1+H20) -> 7092.75 | I19: =H19*(1+I20) -> 8511.3 | J19: =I19*(1+J20) -> 10043.334 | K19: =J19*(1+K20) -> 11549.834 | L19: Proj: prior year × (1 + growth) · value-added services
A20: YoY growth | C20: =C19/B19-1 -> 0.18865672 | D20: =D19/C19-1 -> 0.24510296 | E20: =E19/D19-1 -> 0.28963292 | F20: =F19/E19-1 -> 0.26775102 | G20: 0.4 | H20: 0.25 | I20: 0.2 | J20: 0.18 | K20: 0.15 | L20: FY26P 40%: Q3 FY26 +45%; FY25 +27%; fades as the base grows
A21: Gross revenues | B21: =B15+B16+B17+B19 -> 32472 | C21: =C15+C16+C17+C19 -> 39605 | D21: =D15+D16+D17+D19 -> 44950 | E21: =E15+E16+E17+E19 -> 49690 | F21: =F15+F16+F17+F19 -> 55751 | G21: =G15+G16+G17+G19 -> 64037.38 | H21: =H15+H16+H17+H19 -> 71140.674 | I21: =I15+I16+I17+I19 -> 78794.619 | ... K21: =K15+K16+K17+K19 -> 94754.629 | L21: Formula: Sum of the four revenue lines
A22: YoY growth | C22: =C21/B21-1 -> 0.21966617 | D22: =D21/C21-1 -> 0.13495771 | E22: =E21/D21-1 -> 0.1054505 | F22: =F21/E21-1 -> 0.12197625 | G22: =G21/F21-1 -> 0.14863195 | H22: =H21/G21-1 -> 0.11092417 | I22: =I21/H21-1 -> 0.10758888 | J22: =J21/I21-1 -> 0.098758202 | K22: =K21/J21-1 -> 0.094464668
A23: Less: Client incentives | B23: =Data!C16 -> 8367 | C23: =Data!D16 -> 10295 | D23: =Data!E16 -> 12297 | E23: =Data!F16 -> 13764 | F23: =Data!G16 -> 15751 | G23: =G38*G21 -> 18442.765 | H23: =H38*H21 -> 20773.077 | I23: =I38*I21 -> 23244.413 | J23: =J38*J21 -> 25799.718 | K23: =K38*K21 -> 28426.389 | L23: Proj: Gross revenues × incentive rate
A24: Total net revenues | B24: =B21-B23 -> 24105 | C24: =C21-C23 -> 29310 | D24: =D21-D23 -> 32653 | E24: =E21-E23 -> 35926 | F24: =F21-F23 -> 40000 | G24: =G21-G23 -> 45594.615 | H24: =H21-H23 -> 50367.597 | I24: =I21-I23 -> 55550.206 | ... K24: =K21-K23 -> 66328.24 | L24: Formula: Gross revenues – Client incentives
A25: YoY growth | C25: =C24/B24-1 -> 0.2159303 | D25: =D24/C24-1 -> 0.11405664 | E25: =E24/D24-1 -> 0.10023581 | F25: =F24/E24-1 -> 0.11339977 | G25: =G24/F24-1 -> 0.13986536 | H25: =H24/G24-1 -> 0.10468303 | I25: =I24/H24-1 -> 0.10289571 | J25: =J24/I24-1 -> 0.094082635 | K25: =K24/J24-1 -> 0.091346535 | L25: Check: FY26 9M actual net revenue growth was +15.3% (Q3 FY26 release)
A26: Check: vs reported net revenue (should be 0) | B26: =B24-Data!C17 -> 0 | C26: =C24-Data!D17 -> 0 | D26: =D24-Data!E17 -> 0 | E26: =E24-Data!F17 -> 0 | F26: =F24-Data!G17 -> 0 | L26: Ties to 10-K net revenue
A28: Revenue mix (% of gross revenues)
A29: Service | B29: =B15/B21 -> 0.35338137 | C29: =C15/C21 -> 0.33735639 | D29: =D15/D21 -> 0.32983315 | E29: =E15/E21 -> 0.3242906 | F29: =F15/F21 -> 0.31459525 | G29: =G15/G21 -> 0.30977845 | H29: =H15/H21 -> 0.30352662 | I29: =I15/I21 -> 0.29827832 | ... K29: =K15/K21 -> 0.28972878
A30: Data processing | B30: =B16/B21 -> 0.39393939 | C30: =C16/C21 -> 0.36454993 | D30: =D16/D21 -> 0.35610679 | E30: =E16/E21 -> 0.35649024 | F30: =F16/F21 -> 0.3586124 | G30: =G16/G21 -> 0.36270222 | H30: =H16/H21 -> 0.36021064 | I30: =I16/I21 -> 0.35876134 | ... K30: =K16/K21 -> 0.35626113
A31: International transaction | B31: =B17/B21 -> 0.20109633 | C31: =C17/C21 -> 0.24782224 | D31: =D17/D21 -> 0.2589099 | E31: =E17/E21 -> 0.25488026 | F31: =F17/F21 -> 0.2540941 | G31: =G17/G21 -> 0.23891171 | H31: =H17/H21 -> 0.23656239 | I31: =I17/I21 -> 0.23494154 | ... K31: =K17/K21 -> 0.23211806
A32: Other | B32: =B19/B21 -> 0.051582902 | C32: =C19/C21 -> 0.05027143 | D32: =D19/D21 -> 0.055150167 | E32: =E19/E21 -> 0.064338901 | F32: =F19/F21 -> 0.072698248 | G32: =G19/G21 -> 0.088607623 | H32: =H19/H21 -> 0.099700349 | I32: =I19/I21 -> 0.1080188 | ... K32: =K19/K21 -> 0.12189203
A34: Efficiency metrics — the 'toll'
A35: Core take rate (%) | B35: =B24/(B7*1000) -> 0.0023177885 | C35: =C24/(C7*1000) -> 0.0025267241 | D35: =D24/(D7*1000) -> 0.0026547154 | E35: =E24/(E7*1000) -> 0.0027216667 | F35: =F24/(F7*1000) -> 0.0028169014 | G35: =G24/(G7*1000) -> 0.0029189894 | H35: =H24/(H7*1000) -> 0.0029857019 | I35: =I24/(I7*1000) -> 0.003048998 | ... K35: =K24/(K7*1000) -> 0.003165029 | L35: Formula: Net revenues / (Payments volume × 1,000)
A36: Core take rate (bps) | B36: =B35*10000 -> 23.177885 | C36: =C35*10000 -> 25.267241 | D36: =D35*10000 -> 26.547154 | E36: =E35*10000 -> 27.216667 | F36: =F35*10000 -> 28.169014 | G36: =G35*10000 -> 29.189894 | H36: =H35*10000 -> 29.857019 | I36: =I35*10000 -> 30.48998 | ... K36: =K35*10000 -> 31.65029
A37: Gross take rate (bps) | B37: =B21/(B7*1000)*10000 -> 31.223077 | C37: =C21/(C7*1000)*10000 -> 34.142241 | D37: =D21/(D7*1000)*10000 -> 36.544715 | E37: =E21/(E7*1000)*10000 -> 37.643939 | F37: =F21/(F7*1000)*10000 -> 39.261268 | G37: =G21/(G7*1000)*10000 -> 40.997042 | H37: =H21/(H7*1000)*10000 -> 42.170931 | I37: =I21/(I7*1000)*10000 -> 43.248198 | ... K37: =K21/(K7*1000)*10000 -> 45.2147 | L37: Gross revenues / Payments volume, before incentives
A38: Client incentives (% of gross revenues) | B38: =B23/B21 -> 0.25766814 | C38: =C23/C21 -> 0.25994193 | D38: =D23/D21 -> 0.27357063 | E38: =E23/E21 -> 0.27699738 | F38: =F23/F21 -> 0.28252408 | G38: 0.288 | H38: 0.292 | I38: 0.295 | J38: 0.298 | K38: 0.3 | L38: Proj input: keeps rising ~0.3–0.5 pt a year (FY21 25.8% → FY25 28.3%); Q3 FY26 incentives +18%
A39: Service revenue yield (bps of payments volume) | B39: =B15/(B7*1000)*10000 -> 11.033654 | C39: =C15/(C7*1000)*10000 -> 11.518103 | D39: =D15/(D7*1000)*10000 -> 12.053659 | E39: =E15/(E7*1000)*10000 -> 12.207576 | F39: =F15/(F7*1000)*10000 -> 12.351408 | G39: 12.7 | H39: 12.8 | I39: 12.9 | J39: 13 | K39: 13.1 | L39: Proj input: +0.1–0.35 bps a year (FY21 11.0 → FY25 12.35); Q3 FY26 service revenue +14%
A40: Data processing revenue per transaction ($) | B40: =B16/(B9*1000) -> 0.077668488 | C40: =C16/(C9*1000) -> 0.075002597 | D40: =D16/(D9*1000) -> 0.075291627 | E40: =E16/(E9*1000) -> 0.075765612 | F40: =F16/(F9*1000) -> 0.077642718 | G40: 0.082 | H40: 0.083 | I40: 0.084 | J40: 0.085 | K40: 0.086 | L40: Proj input: FY25 $0.078; Q3 FY26 DP revenue +17% on transactions +10% implies ~$0.082
A41: Net revenue per transaction ($) | B41: =B24/(B9*1000) -> 0.14635701 | C41: =C24/(C9*1000) -> 0.15225974 | D41: =D24/(D9*1000) -> 0.1535889 | E41: =E24/(E9*1000) -> 0.15366125 | F41: =F24/(F9*1000) -> 0.15533981 | G41: =G24/(G9*1000) -> 0.16096951 | H41: =H24/(H9*1000) -> 0.16313788 | I41: =I24/(I9*1000) -> 0.16506795 | ... K41: =K24/(K9*1000) -> 0.16897718 | L41: All-in 'toll' per swipe
A43: Notes
A44: 1. Timing: payments volume covers the 12 months to Sep 30, but Visa prices service revenue on the PRIOR quarter's payments volume. Net revenue therefore reflects roughly Jul–Jun volume, while the denominator is Oct–Sep. It is a timing effect, not a pricing change.
A45: 2. Average transaction size is a proxy: payments volume (all Visa-branded payments, excl. cash) and processed transactions (VisaNet only, incl. some cash) do not cover exactly the same universe.
A46: 3. FY21 international revenue was depressed by COVID travel restrictions; the FY22 jump (+50%) is cross-border recovery, so FY21→FY22 growth rates overstate the run-rate.
A47: 4. Projections (base case): revenue is built bottom-up — service = volume × yield, data processing = transactions × price per transaction, international and other grow at input rates, incentives = % of gross. FY26P is calibrated to the nine months to Jun 30, 2026 (Q3 FY26 8-K). FY26 actuals arrive with the 10-K in mid-November 2026 and will replace FY26P.

Sheet Tab2_Core_Returns
A1: Tab 2 — 3-Statement Core & Returns
A2: Visa Inc. · $ in millions unless noted · FY ends Sep 30 · green = link · black = formula · blue = assumption (yellow = base-case projection input)
A4: Assumptions
A5: Treat investment securities as cash in invested capital? (1 = yes, 0 = no) | B5: 1 | L5: 1 = subtract cash + current & non-current investment securities. Litigation escrow is never subtracted: it is restricted cash earmarked for settlements.
A6: FY21 normalised tax rate | B6: 0.17 | L6: Visa's FY21 non-GAAP effective tax rate (Q4 FY21 release). GAAP 23.4% includes a ~$1.0B one-off deferred-tax remeasurement.
B7: Historical (audited) | G7: Projections — base case
A8: Line item | B8: FY21 | C8: FY22 | D8: FY23 | E8: FY24 | F8: FY25 | G8: FY26P | H8: FY27P | I8: FY28P | J8: FY29P | K8: FY30P | L8: Formula / note
A10: Income statement essentials
A11: Total net revenues | B11: =Tab1_Drivers!B24 -> 24105 | C11: =Tab1_Drivers!C24 -> 29310 | D11: =Tab1_Drivers!D24 -> 32653 | E11: =Tab1_Drivers!E24 -> 35926 | F11: =Tab1_Drivers!F24 -> 40000 | G11: =Tab1_Drivers!G24 -> 45594.615 | H11: =Tab1_Drivers!H24 -> 50367.597 | I11: =Tab1_Drivers!I24 -> 55550.206 | ... K11: =Tab1_Drivers!K24 -> 66328.24 | L11: Link: Tab 1 total net revenues
A12: Operating expenses ex-litigation | B12: =Data!C27-Data!C26 -> 8298 | C12: =Data!D27-Data!D26 -> 9629 | D12: =Data!E27-Data!E26 -> 10726 | E12: =Data!F27-Data!F26 -> 11869 | F12: =Data!G27-Data!G26 -> 13444 | G12: =G11*G13 -> 15502.169 | H12: =H11*H13 -> 17024.248 | I12: =I11*I13 -> 18664.869 | J12: =J11*J13 -> 20299.356 | K12: =K11*K13 -> 22020.976 | L12: Hist: Data (total opex – litigation) · Proj: Net revenues × opex ratio
A13: Opex ex-litigation (% of net revenues) | B13: =B12/B11 -> 0.34424393 | C13: =C12/C11 -> 0.32852269 | D13: =D12/D11 -> 0.32848437 | E13: =E12/E11 -> 0.33037355 | F13: =F12/F11 -> 0.3361 | G13: 0.34 | H13: 0.338 | I13: 0.336 | J13: 0.334 | K13: 0.332 | L13: FY26P 34.0%: 9M FY26 actual 34.4% incl. ~$0.6B severance; then –0.2 pt a year (modest leverage, consistent with DOL ~1.0x)
A14: Litigation provision | B14: =Data!C26 -> 3 | C14: =Data!D26 -> 868 | D14: =Data!E26 -> 927 | E14: =Data!F26 -> 462 | F14: =Data!G26 -> 2562 | G14: 1290 | H14: 500 | I14: 500 | J14: 500 | K14: 500 | L14: FY26P = 9M FY26 actual ($1,290M), no Q4 assumed · FY27P+ $500M/yr placeholder (does not affect ex-litigation metrics)
A15: Operating expenses (total, GAAP) | B15: =Data!C27 -> 8301 | C15: =Data!D27 -> 10497 | D15: =Data!E27 -> 11653 | E15: =Data!F27 -> 12331 | F15: =Data!G27 -> 16006 | G15: =G12+G14 -> 16792.169 | H15: =H12+H14 -> 17524.248 | I15: =I12+I14 -> 19164.869 | J15: =J12+J14 -> 20799.356 | K15: =K12+K14 -> 22520.976 | L15: Proj: Opex ex-litigation + litigation provision
A16: Operating income (EBIT) — GAAP | B16: =B11-B15 -> 15804 | C16: =C11-C15 -> 18813 | D16: =D11-D15 -> 21000 | E16: =E11-E15 -> 23595 | F16: =F11-F15 -> 23994 | G16: =G11-G15 -> 28802.446 | H16: =H11-H15 -> 32843.349 | I16: =I11-I15 -> 36385.337 | ... K16: =K11-K15 -> 43807.264 | L16: Formula: Net revenues – Operating expenses
A17: Operating margin (%) — GAAP | B17: =B16/B11 -> 0.65563161 | C17: =C16/C11 -> 0.64186285 | D17: =D16/D11 -> 0.64312621 | E17: =E16/E11 -> 0.65676669 | F17: =F16/F11 -> 0.59985 | G17: =G16/G11 -> 0.63170718 | H17: =H16/H11 -> 0.65207298 | I17: =I16/I11 -> 0.65499913 | ... K17: =K16/K11 -> 0.66046173
A18: Check: vs reported operating income (should be 0) | B18: =B16-Data!C31 -> 0 | C18: =C16-Data!D31 -> 0 | D18: =D16-Data!E31 -> 0 | E18: =E16-Data!F31 -> 0 | F18: =F16-Data!G31 -> 0 | L18: Ties to 10-K
A19: EBIT ex-litigation (analytical) | B19: =B16+B14 -> 15807 | C19: =C16+C14 -> 19681 | D19: =D16+D14 -> 21927 | E19: =E16+E14 -> 24057 | F19: =F16+F14 -> 26556 | G19: =G16+G14 -> 30092.446 | H19: =H16+H14 -> 33343.349 | I19: =I16+I14 -> 36885.337 | ... K19: =K16+K14 -> 44307.264 | L19: Formula: GAAP EBIT + litigation provision · used for ROIC in Tab 3
A20: Operating margin (%) — ex-litigation | B20: =B19/B11 -> 0.65575607 | C20: =C19/C11 -> 0.67147731 | D20: =D19/D11 -> 0.67151563 | E20: =E19/E11 -> 0.66962645 | F20: =F19/F11 -> 0.6639 | G20: =G19/G11 -> 0.66 | H20: =H19/H11 -> 0.662 | I20: =I19/I11 -> 0.664 | ... K20: =K19/K11 -> 0.668
A21: Memo: EBIT on Visa's non-GAAP basis | B21: =B11-Data!C28 -> 16028 | C21: =C11-Data!D28 -> 19923 | D21: =D11-Data!E28 -> 22172 | E21: =E11-Data!F28 -> 24317 | F21: =F11-Data!G28 -> 27094 | L21: Hist only: Net revenues – Visa non-GAAP opex
A22: Operating margin (%) — Visa non-GAAP | B22: =B21/B11 -> 0.66492429 | C22: =C21/C11 -> 0.67973388 | D22: =D21/D11 -> 0.67901877 | E22: =E21/E11 -> 0.67686355 | F22: =F21/F11 -> 0.67735
A23: Non-operating income (expense) | B23: =Data!C33 -> 259 | C23: =Data!D33 -> -677 | D23: =Data!E33 -> 37 | E23: =Data!F33 -> 321 | F23: =Data!G33 -> 200 | G23: -150 | H23: -150 | I23: -150 | J23: -150 | K23: -150 | L23: FY26P: 9M FY26 actual –$115M; held at –$150M (interest cost ~ investment income)
A24: Pre-tax income | B24: =Data!C34 -> 16063 | C24: =Data!D34 -> 18136 | D24: =Data!E34 -> 21037 | E24: =Data!F34 -> 23916 | F24: =Data!G34 -> 24194 | G24: =G16+G23 -> 28652.446 | H24: =H16+H23 -> 32693.349 | I24: =I16+I23 -> 36235.337 | J24: =J16+J23 -> 39827.16 | K24: =K16+K23 -> 43657.264 | L24: Proj: EBIT + non-operating
A25: Income tax provision | B25: =Data!C35 -> 3752 | C25: =Data!D35 -> 3179 | D25: =Data!E35 -> 3764 | E25: =Data!F35 -> 4173 | F25: =Data!G35 -> 4136 | G25: =G24*G26 -> 4584.3913 | H25: =H24*H26 -> 5557.8693 | I25: =I24*I26 -> 6160.0073 | J25: =J24*J26 -> 6770.6171 | K25: =K24*K26 -> 7421.735 | L25: Proj: Pre-tax income × tax rate
A26: Tax rate (%) — GAAP effective | B26: =B25/B24 -> 0.23358028 | C26: =C25/C24 -> 0.17528672 | D26: =D25/D24 -> 0.17892285 | E26: =E25/E24 -> 0.1744857 | F26: =F25/F24 -> 0.17095148 | G26: 0.16 | H26: 0.17 | I26: 0.17 | J26: 0.17 | K26: 0.17 | L26: FY26P 16.0%: 9M FY26 actual 15.6% · then 17.0% (FY23–25 range 17.1–17.9%)
A27: Tax rate (%) — normalised (for NOPAT) | B27: =$B$6 -> 0.17 | C27: =C26 -> 0.17528672 | D27: =D26 -> 0.17892285 | E27: =E26 -> 0.1744857 | F27: =F26 -> 0.17095148 | G27: =G26 -> 0.16 | H27: =H26 -> 0.17 | I27: =I26 -> 0.17 | J27: =J26 -> 0.17 | K27: =K26 -> 0.17 | L27: FY21 = assumption B6; other years = effective rate
A28: Net income | B28: =Data!C36 -> 12311 | C28: =Data!D36 -> 14957 | D28: =Data!E36 -> 17273 | E28: =Data!F36 -> 19743 | F28: =Data!G36 -> 20058 | G28: =G24-G25 -> 24068.054 | H28: =H24-H25 -> 27135.48 | I28: =I24-I25 -> 30075.33 | J28: =J24-J25 -> 33056.543 | K28: =K24-K25 -> 36235.53 | L28: Proj: Pre-tax income – tax
A29: Net margin (%) | B29: =B28/B11 -> 0.51072392 | C29: =C28/C11 -> 0.51030365 | D29: =D28/D11 -> 0.52898662 | E29: =E28/E11 -> 0.54954629 | F29: =F28/F11 -> 0.50145 | G29: =G28/G11 -> 0.52787055 | H29: =H28/H11 -> 0.53874875 | I29: =I28/I11 -> 0.54140806 | ... K29: =K28/K11 -> 0.54630621
A31: Operating leverage
A32: Payments volume growth | C32: =Tab1_Drivers!C8 -> 0.11538462 | D32: =Tab1_Drivers!D8 -> 0.060344828 | E32: =Tab1_Drivers!E8 -> 0.073170732 | F32: =Tab1_Drivers!F8 -> 0.075757576 | G32: =Tab1_Drivers!G8 -> 0.1 | H32: =Tab1_Drivers!H8 -> 0.08 | I32: =Tab1_Drivers!I8 -> 0.08 | J32: =Tab1_Drivers!J8 -> 0.075 | K32: =Tab1_Drivers!K8 -> 0.07 | L32: Link: Tab 1
A33: Net revenue growth | C33: =C11/B11-1 -> 0.2159303 | D33: =D11/C11-1 -> 0.11405664 | E33: =E11/D11-1 -> 0.10023581 | F33: =F11/E11-1 -> 0.11339977 | G33: =G11/F11-1 -> 0.13986536 | H33: =H11/G11-1 -> 0.10468303 | I33: =I11/H11-1 -> 0.10289571 | J33: =J11/I11-1 -> 0.094082635 | K33: =K11/J11-1 -> 0.091346535
A34: EBIT growth — GAAP | C34: =C16/B16-1 -> 0.19039484 | D34: =D16/C16-1 -> 0.1162494 | E34: =E16/D16-1 -> 0.12357143 | F34: =F16/E16-1 -> 0.016910362 | G34: =G16/F16-1 -> 0.200402 | H34: =H16/G16-1 -> 0.14029724 | I34: =I16/H16-1 -> 0.1078449 | J34: =J16/I16-1 -> 0.098716215 | K34: =K16/J16-1 -> 0.095807326
A35: EBIT growth — ex-litigation | C35: =C19/B19-1 -> 0.24508129 | D35: =D19/C19-1 -> 0.11412022 | E35: =E19/D19-1 -> 0.097140512 | F35: =F19/E19-1 -> 0.10387829 | G35: =G19/F19-1 -> 0.13316936 | H35: =H19/G19-1 -> 0.10803055 | I35: =I19/H19-1 -> 0.10622772 | J35: =J19/I19-1 -> 0.097378065 | K35: =K19/J19-1 -> 0.094623852
A36: Degree of operating leverage — GAAP | C36: =C34/C33 -> 0.88174208 | D36: =D34/D33 -> 1.0192252 | E36: =E34/E33 -> 1.2328072 | F36: =F34/F33 -> 0.14912167 | G36: =G34/G33 -> 1.4328208 | H36: =H34/H33 -> 1.34021 | I36: =I34/I33 -> 1.0480992 | J36: =J34/J33 -> 1.0492501 | K36: =K34/K33 -> 1.0488337 | L36: Formula: %Δ EBIT / %Δ Net revenues
A37: Degree of operating leverage — ex-litigation | C37: =C35/C33 -> 1.1350018 | D37: =D35/D33 -> 1.0005575 | E37: =E35/E33 -> 0.96911981 | F37: =F35/F33 -> 0.91603618 | G37: =G35/G33 -> 0.95212538 | H37: =H35/H33 -> 1.0319777 | I37: =I35/I33 -> 1.0323824 | J37: =J35/J33 -> 1.035027 | K37: =K35/K33 -> 1.0358778 | L37: Core operating leverage, litigation noise removed
A38: Incremental EBIT margin — ex-litigation | C38: =(C19-B19)/(C11-B11) -> 0.74428434 | D38: =(D19-C19)/(D11-C11) -> 0.67185163 | E38: =(E19-D19)/(E11-D11) -> 0.6507791 | F38: =(F19-E19)/(F11-E11) -> 0.61340206 | G38: =(G19-F19)/(G11-F11) -> 0.63211604 | H38: =(H19-G19)/(H11-G11) -> 0.68110529 | I38: =(I19-H19)/(I11-H11) -> 0.68343716 | J38: =(J19-I19)/(J11-I11) -> 0.68725791 | K38: =(K19-J19)/(K11-J11) -> 0.68989465 | L38: Formula: Δ EBIT ex-lit / Δ Net revenues
A39: Cumulative incremental EBIT margin — ex-litigation | F39: =(F19-B19)/(F11-B11) -> 0.67625039 | K39: =(K19-F19)/(K11-F11) -> 0.67422905 | L39: FY25 column: FY21→FY25 · FY30P column: FY25→FY30P
A40: Margin change — ex-litigation | C40: =(C20-B20)*10000 -> 157.21244 | D40: =(D20-C20)*10000 -> 0.38322594 | E40: =(E20-D20)*10000 -> -18.891797 | F40: =(F20-E20)*10000 -> -57.264544 | G40: =(G20-F20)*10000 -> -39 | H40: =(H20-G20)*10000 -> 20 | I40: =(I20-H20)*10000 -> 20 | J40: =(J20-I20)*10000 -> 20 | K40: =(K20-J20)*10000 -> 20
A42: Balance sheet essentials
A43: Cash & cash equivalents | B43: =Data!C39 -> 16487 | C43: =Data!D39 -> 15689 | D43: =Data!E39 -> 16286 | E43: =Data!F39 -> 11975 | F43: =Data!G39 -> 17164 | G43: =F43+G62-Tab4_Capital_Allocation!G11-Tab4_Capital_Allocation!G12-G53+(G49-F49) -> 10718.75 | H43: =G43+H62-Tab4_Capital_Allocation!H11-Tab4_Capital_Allocation!H12-H53+(H49-G49) -> 11275.524 | I43: =H43+I62-Tab4_Capital_Allocation!I11-Tab4_Capital_Allocation!I12-I53+(I49-H49) -> 11979.291 | J43: =I43+J62-Tab4_Capital_Allocation!J11-Tab4_Capital_Allocation!J12-J53+(J49-I49) -> 12832.118 | K43: =J43+K62-Tab4_Capital_Allocation!K11-Tab4_Capital_Allocation!K12-K53+(K49-J49) -> 13843.894 | L43: Proj: prior + FCF – dividends – buybacks – acquisitions + net debt issuance
A44: Memo: minimum operating cash balance | G44: 5000 | H44: 5000 | I44: 5000 | J44: 5000 | K44: 5000 | L44: Input: floor for the check below (Visa has held $12–17B; settlement needs make a floor sensible)
A45: Check: projected cash above minimum (1 = OK, 0 = raise debt or cut buybacks) | G45: =IF(G43>=G44,1,0) -> 1 | H45: =IF(H43>=H44,1,0) -> 1 | I45: =IF(I43>=I44,1,0) -> 1 | J45: =IF(J43>=J44,1,0) -> 1 | K45: =IF(K43>=K44,1,0) -> 1 | L45: Stress test: returning 150% of FCF every year drives cash to about –$62B by FY30P — this flag catches it
A46: Investment securities (current + non-current) | B46: =Data!C41+Data!C42 -> 3730 | C46: =Data!D41+Data!D42 -> 4969 | D46: =Data!E41+Data!E42 -> 5763 | E46: =Data!F41+Data!F42 -> 5745 | F46: =Data!G41+Data!G42 -> 2832 | G46: =F46 -> 2832 | H46: =G46 -> 2832 | I46: =H46 -> 2832 | J46: =I46 -> 2832 | K46: =J46 -> 2832 | L46: Proj: held flat
A47: Cash deducted in invested capital | B47: =B43+$B$5*B46 -> 20217 | C47: =C43+$B$5*C46 -> 20658 | D47: =D43+$B$5*D46 -> 22049 | E47: =E43+$B$5*E46 -> 17720 | F47: =F43+$B$5*F46 -> 19996 | G47: =G43+$B$5*G46 -> 13550.75 | H47: =H43+$B$5*H46 -> 14107.524 | I47: =I43+$B$5*I46 -> 14811.291 | ... K47: =K43+$B$5*K46 -> 16675.894 | L47: Formula: Cash + (switch B5 × investment securities)
A48: Memo: Restricted cash — litigation escrow (not deducted) | B48: =Data!C40 -> 894 | C48: =Data!D40 -> 1449 | D48: =Data!E40 -> 1764 | E48: =Data!F40 -> 3089 | F48: =Data!G40 -> 2990 | L48: Hist only · restricted, treated as operating
A49: Total debt (short-term + long-term) | B49: =Data!C45+Data!C46 -> 20977 | C49: =Data!D45+Data!D46 -> 22450 | D49: =Data!E45+Data!E46 -> 20463 | E49: =Data!F45+Data!F46 -> 20836 | F49: =Data!G45+Data!G46 -> 25171 | G49: 23858 | H49: 23858 | I49: 23858 | J49: 23858 | K49: 23858 | L49: FY26P = Jun 30, 2026 actual $23,858M (Q3 FY26 release) · held flat (maturities refinanced)
A50: Total shareholders' equity | B50: =Data!C48 -> 37589 | C50: =Data!D48 -> 35581 | D50: =Data!E48 -> 38733 | E50: =Data!F48 -> 39137 | F50: =Data!G48 -> 37909 | G50: =F50+G28-Tab4_Capital_Allocation!G11-Tab4_Capital_Allocation!G12 -> 35983.556 | H50: =G50+H28-Tab4_Capital_Allocation!H11-Tab4_Capital_Allocation!H12 -> 37340.33 | I50: =H50+I28-Tab4_Capital_Allocation!I11-Tab4_Capital_Allocation!I12 -> 38844.096 | J50: =I50+J28-Tab4_Capital_Allocation!J11-Tab4_Capital_Allocation!J12 -> 40496.923 | K50: =J50+K28-Tab4_Capital_Allocation!K11-Tab4_Capital_Allocation!K12 -> 42308.7 | L50: Proj: prior + net income – dividends – buybacks (ignores share-based comp and OCI)
A51: Invested capital | B51: =B49+B50-B47 -> 38349 | C51: =C49+C50-C47 -> 37373 | D51: =D49+D50-D47 -> 37147 | E51: =E49+E50-E47 -> 42253 | F51: =F49+F50-F47 -> 43084 | G51: =G49+G50-G47 -> 46290.805 | H51: =H49+H50-H47 -> 47090.805 | I51: =I49+I50-I47 -> 47890.805 | ... K51: =K49+K50-K47 -> 49490.805 | L51: Formula: Total debt + Equity – Cash
A52: Average invested capital | C52: =AVERAGE(B51,C51) -> 37861 | D52: =AVERAGE(C51,D51) -> 37260 | E52: =AVERAGE(D51,E51) -> 39700 | F52: =AVERAGE(E51,F51) -> 42668.5 | G52: =AVERAGE(F51,G51) -> 44687.403 | H52: =AVERAGE(G51,H51) -> 46690.805 | I52: =AVERAGE(H51,I51) -> 47490.805 | J52: =AVERAGE(I51,J51) -> 48290.805 | K52: =AVERAGE(J51,K51) -> 49090.805 | L52: Formula: (Opening + Closing) / 2
A53: Acquisitions (cash paid) | G53: 800 | H53: 800 | I53: 800 | J53: 800 | K53: 800 | L53: Proj input: FY21–25 average ≈ $765M/yr (cash flow statement: 75 / 1,948 / 0 / 915 / 887) · added to goodwill, paid from cash
A54: Goodwill | B54: =Data!C43 -> 15958 | C54: =Data!D43 -> 17787 | D54: =Data!E43 -> 17997 | E54: =Data!F43 -> 18941 | F54: =Data!G43 -> 19879 | G54: =F54+G53 -> 20679 | H54: =G54+H53 -> 21479 | I54: =H54+I53 -> 22279 | J54: =I54+J53 -> 23079 | K54: =J54+K53 -> 23879 | L54: Proj: prior + acquisitions (simplification: whole price booked as goodwill)
A55: Intangible assets, net | B55: =Data!C44 -> 27664 | C55: =Data!D44 -> 25065 | D55: =Data!E44 -> 26104 | E55: =Data!F44 -> 26889 | F55: =Data!G44 -> 27646 | G55: =F55 -> 27646 | H55: =G55 -> 27646 | I55: =H55 -> 27646 | J55: =I55 -> 27646 | K55: =J55 -> 27646 | L55: Proj: flat (mostly indefinite-lived Visa Europe rights)
A56: Invested capital ex-goodwill | B56: =B51-B54 -> 22391 | C56: =C51-C54 -> 19586 | D56: =D51-D54 -> 19150 | E56: =E51-E54 -> 23312 | F56: =F51-F54 -> 23205 | G56: =G51-G54 -> 25611.805 | H56: =H51-H54 -> 25611.805 | I56: =I51-I54 -> 25611.805 | ... K56: =K51-K54 -> 25611.805 | L56: Formula: Invested capital – Goodwill
A57: Memo: Tangible invested capital (ex-goodwill & intangibles) | B57: =B51-B54-B55 -> -5273 | C57: =C51-C54-C55 -> -5479 | D57: =D51-D54-D55 -> -6954 | E57: =E51-E54-E55 -> -3577 | F57: =F51-F54-F55 -> -4441 | G57: =G51-G54-G55 -> -2034.1946 | H57: =H51-H54-H55 -> -2034.1946 | I57: =I51-I54-I55 -> -2034.1946 | ... K57: =K51-K54-K55 -> -2034.1946 | L57: Negative = the network runs on other people's money
A59: Cash flow essentials
A60: Operating cash flow (OCF) | B60: =Data!C52 -> 15227 | C60: =Data!D52 -> 18849 | D60: =Data!E52 -> 20755 | E60: =Data!F52 -> 19950 | F60: =Data!G52 -> 23059 | G60: =G62+G61 -> 23257.06 | H60: =H62+H61 -> 28948.713 | I60: =I62+I61 -> 32075.137 | J60: =J62+J61 -> 35244.497 | K60: =K62+K61 -> 38623.346 | L60: Proj: FCF + CapEx
A61: Capital expenditures (CapEx) | B61: =Data!C53 -> 705 | C61: =Data!D53 -> 970 | D61: =Data!E53 -> 1059 | E61: =Data!F53 -> 1257 | F61: =Data!G53 -> 1482 | G61: =G11*G65 -> 1595.8115 | H61: =H11*H65 -> 1813.2335 | I61: =I11*I65 -> 1999.8074 | J61: =J11*J65 -> 2187.9546 | K61: =K11*K65 -> 2387.8166 | L61: Proj: Net revenues × capital intensity
A62: Free cash flow (FCF) | B62: =B60-B61 -> 14522 | C62: =C60-C61 -> 17879 | D62: =D60-D61 -> 19696 | E62: =E60-E61 -> 18693 | F62: =F60-F61 -> 21577 | G62: =G28*G64 -> 21661.249 | H62: =H28*H64 -> 27135.48 | I62: =I28*I64 -> 30075.33 | J62: =J28*J64 -> 33056.543 | K62: =K28*K64 -> 36235.53 | L62: Hist: OCF – CapEx · Proj: Net income × FCF conversion
A63: FCF margin (%) | B63: =B62/B11 -> 0.60244762 | C63: =C62/C11 -> 0.60999659 | D63: =D62/D11 -> 0.60319113 | E63: =E62/E11 -> 0.52031955 | F63: =F62/F11 -> 0.539425 | G63: =G62/G11 -> 0.4750835 | H63: =H62/H11 -> 0.53874875 | I63: =I62/I11 -> 0.54140806 | ... K63: =K62/K11 -> 0.54630621
A64: FCF conversion rate (%) | B64: =B62/B28 -> 1.1795955 | C64: =C62/C28 -> 1.19536 | D64: =D62/D28 -> 1.1402767 | E64: =E62/E28 -> 0.94681659 | F64: =F62/F28 -> 1.0757304 | G64: 0.9 | H64: 1 | I64: 1 | J64: 1 | K64: 1 | L64: FY26P 90%: 9M FY26 actual 87% (higher cash taxes/litigation payments) · then 100% (below the 5-yr avg of 113%)
A65: Capital intensity (%) | B65: =B61/B11 -> 0.029247044 | C65: =C61/C11 -> 0.033094507 | D65: =D61/D11 -> 0.032431936 | E65: =E61/E11 -> 0.034988588 | F65: =F61/F11 -> 0.03705 | G65: 0.035 | H65: 0.036 | I65: 0.036 | J65: 0.036 | K65: 0.036 | L65: FY26P 3.5%: 9M FY26 actual 3.5% · then 3.6%
A66: CapEx / D&A | B66: =B61/Data!C24 -> 0.87686567 | C66: =C61/Data!D24 -> 1.126597 | D66: =D61/Data!E24 -> 1.1230117 | E66: =E61/Data!F24 -> 1.2156673 | F66: =F61/Data!G24 -> 1.2147541 | L66: Hist only
A67: Incremental FCF margin | C67: =(C62-B62)/(C11-B11) -> 0.64495677 | D67: =(D62-C62)/(D11-C11) -> 0.54352378 | E67: =(E62-D62)/(E11-D11) -> -0.30644668 | F67: =(F62-E62)/(F11-E11) -> 0.70790378 | G67: =(G62-F62)/(G11-F11) -> 0.015058925 | H67: =(H62-G62)/(H11-G11) -> 1.1469204 | I67: =(I62-H62)/(I11-H11) -> 0.56725284 | J67: =(J62-I62)/(J11-I11) -> 0.57042406 | K67: =(K62-J62)/(K11-J11) -> 0.57261256 | L67: Formula: Δ FCF / Δ Net revenues
A68: Cumulative incremental FCF margin | F68: =(F62-B62)/(F11-B11) -> 0.44385027 | K68: =(K62-F62)/(K11-F11) -> 0.5567607 | L68: FY25 column: FY21→FY25 · FY30P column: FY25→FY30P
A70: Notes
A71: 1. Operating leverage: ex-litigation, Visa's DOL is about 1.0x across FY22–FY25, so margins are roughly flat (~66–67%). The 'toll road' leverage shows up in capital, not opex: each new revenue dollar needs only ~3–4 cents of CapEx.
A72: 2. Tangible invested capital is NEGATIVE in every year: the operating network is funded by operating liabilities (client-incentive accruals, settlement obligations, deferred taxes), not shareholder capital.
A73: 3. FY24 OCF dipped (–4%) mainly because cash taxes rose to $5.8B from $3.4B in FY23, which pulled FCF conversion below 100%.
A74: 4. Projections (base case): opex ex-litigation as % of revenue, tax rate, FCF conversion and capital intensity are inputs (yellow), calibrated to the nine months to Jun 30, 2026. Balance sheet rolls forward: equity + net income – capital returned; cash + FCF – capital returned + net debt issuance. Invested capital therefore grows by (net income – FCF + acquisitions) each year — mostly acquisitions, because FCF ≈ net income. Share-based compensation (which also adds to equity) is ignored, so projected capital is slightly understated and projected ROIC slightly overstated.

Sheet Tab3_ROIC_WACC
A1: Tab 3 — ROIC vs WACC Analysis (the 'Moat' tab)
A2: Visa Inc. · $ in millions unless noted · market inputs as of Oct 15, 2026 · blue = input · black = formula · green = link · yellow = judgement call
A4: WACC inputs — Metric | Value | Source / formula
A5: Cost of equity (CAPM)
A6: Risk-free rate (10-year U.S. Treasury par yield) | B6: 0.0519 | C6: U.S. Treasury Daily Par Yield Curve, 10 Yr, Oct 14, 2026 close (latest official print): 5.19% — https://home.treasury.gov/resource-center/data-chart-center/interest-rates/TextView?type=daily_treasury_yield_curve&field_tdr_date_value_month=202610
A7: Visa raw beta (5-year, monthly vs S&P 500) | B7: 0.77 | C7: Yahoo Finance 'Beta (5Y Monthly)' 0.77 (CNBC shows 0.82) — third-party figures supplied by you; no primary source. Sensitivity grid covers 0.59–1.10
A8: Blume weight on raw beta | B8: 0.67 | C8: Standard Blume adjustment (Bloomberg convention): adjusted β = 0.67 × raw + 0.33 × 1.0
A9: Adjusted beta (used) | B9: =$B$7*$B$8+(1-$B$8)*1 -> 0.8459 | C9: Formula: Blume-adjusted beta — pulls a low raw beta toward 1.0
A10: Equity risk premium | B10: 0.055 | C10: Agreed base case: 5.5% (conservative). Damodaran's implied ERP is 4.20% (Oct 1, 2026) — see memo below the WACC
A11: Cost of equity (Ke) | B11: =$B$6+$B$9*$B$10 -> 0.0984245 | C11: Formula: Rf + β × ERP
A12: Cost of debt
A13: Visa 4.150% senior notes due Dec 14, 2035 — yield (CUSIP 92826CAE2) | B13: 0.0542 | C13: Public.com quote: price 90.95, yield 5.42% (no timestamp; may be yield-to-worst given Jun 2035 par call). Terms: SEC FWP https://www.sec.gov/Archives/edgar/data/1403161/000119312515399417/d102656dfwp.htm · verify last trade on FINRA
A14: Pre-tax cost of debt (market) | B14: =$B$13 -> 0.0542 | C14: Formula: = Visa's traded ~9-year USD bond yield (a marginal cost, not the ~3% book rate)
A15: Tax rate | B15: =Tab2_Core_Returns!F27 -> 0.17095148 | C15: Link: Tab 2 FY25 effective tax rate
A16: After-tax cost of debt (Kd) | B16: =$B$14*(1-$B$15) -> 0.04493443 | C16: Formula: Pre-tax Kd × (1 – tax rate)
A17: Memo: interest expense, 9 months to Jun 30, 2026 | B17: 566 | C17: Q3 FY26 earnings release (8-K) — https://www.sec.gov/Archives/edgar/data/0001403161/000140316126000103/q32026earningsrelease.htm
A18: Capital structure (market values)
A19: Share price ($) — close Oct 14, 2026 | B19: 391.43 | C19: Yahoo Finance close, as supplied (Google Finance prior close $391.46 agrees). Same date as the Treasury yield → one consistent valuation date
A20: As-converted class A shares outstanding (millions) | B20: 1880 | C20: Q3 FY26 Form 10-Q, Note 11 Stockholders' Equity, as-converted table at Jun 30, 2026: class A 1,702 + B-1 3 + B-2 1 + B-3 91 + C 73 + preferred A/B/C 10 = 1,880 — https://www.sec.gov/Archives/edgar/data/1403161/000140316126000104/R20.htm
A21: Market capitalisation | B21: =$B$19*$B$20 -> 735888.4 | C21: Formula: Price × as-converted shares
A22: Total debt (Jun 30, 2026) | B22: 23858 | C22: Q3 FY26 release: current maturities $2,996M + long-term $20,862M · book value as proxy for market value
A23: Memo: effective interest rate on existing debt | B23: =$B$17/0.75/$B$22 -> 0.031631598 | C23: Formula: annualised 9M interest / debt · legacy coupons (2.0–3.9%) are below today's market cost
A24: Equity weight | B24: =$B$21/($B$21+$B$22) -> 0.96859742 | C24: Formula: E / (D + E)
A25: Debt weight | B25: =1-$B$24 -> 0.031402584 | C25: Formula: 1 – equity weight
A26: WACC | B26: =$B$24*$B$11+$B$25*$B$16 -> 0.096744774 | C26: Formula: E-weight × Ke + D-weight × Kd(after-tax)
A27: Memo: implied credit spread (bond yield – Rf) | B27: =$B$14-$B$6 -> 0.0023 | C27: About 0.2%: tight but plausible for an AA- issuer with ~9 years to maturity
A28: Memo: Damodaran implied ERP (Oct 1, 2026) | B28: 0.042 | C28: Damodaran Online home page: trailing-12-month, adjusted payout; prior month 4.14% — https://pages.stern.nyu.edu/~adamodar/New_Home_Page/home.htm
A29: Memo: WACC at Damodaran implied ERP | B29: =$B$24*($B$6+$B$9*$B$28)+$B$25*$B$16 -> 0.086093398 | C29: Formula: same WACC with the market-implied ERP — the 'less conservative' case
A31: Line item | B31: FY21 | C31: FY22 | D31: FY23 | E31: FY24 | F31: FY25 | G31: FY26P | H31: FY27P | I31: FY28P | J31: FY29P | K31: FY30P | L31: Formula / note
A32: ROIC — including goodwill (return on everything shareholders paid, incl. Visa Europe)
A33: EBIT ex-litigation | B33: =Tab2_Core_Returns!B19 -> 15807 | C33: =Tab2_Core_Returns!C19 -> 19681 | D33: =Tab2_Core_Returns!D19 -> 21927 | E33: =Tab2_Core_Returns!E19 -> 24057 | F33: =Tab2_Core_Returns!F19 -> 26556 | G33: =Tab2_Core_Returns!G19 -> 30092.446 | H33: =Tab2_Core_Returns!H19 -> 33343.349 | I33: =Tab2_Core_Returns!I19 -> 36885.337 | ... K33: =Tab2_Core_Returns!K19 -> 44307.264 | L33: Link: Tab 2
A34: Normalised tax rate | B34: =Tab2_Core_Returns!B27 -> 0.17 | C34: =Tab2_Core_Returns!C27 -> 0.17528672 | D34: =Tab2_Core_Returns!D27 -> 0.17892285 | E34: =Tab2_Core_Returns!E27 -> 0.1744857 | F34: =Tab2_Core_Returns!F27 -> 0.17095148 | G34: =Tab2_Core_Returns!G27 -> 0.16 | H34: =Tab2_Core_Returns!H27 -> 0.17 | I34: =Tab2_Core_Returns!I27 -> 0.17 | ... K34: =Tab2_Core_Returns!K27 -> 0.17 | L34: Link: Tab 2 (FY21 normalised to 17.0%)
A35: NOPAT | B35: =B33*(1-B34) -> 13119.81 | C35: =C33*(1-C34) -> 16231.182 | D35: =D33*(1-D34) -> 18003.759 | E35: =E33*(1-E34) -> 19859.398 | F35: =F33*(1-F34) -> 22016.213 | G35: =G33*(1-G34) -> 25277.654 | H35: =H33*(1-H34) -> 27674.98 | I35: =I33*(1-I34) -> 30614.83 | ... K35: =K33*(1-K34) -> 36775.03 | L35: Formula: EBIT × (1 – tax rate)
A36: Invested capital — ending | B36: =Tab2_Core_Returns!B51 -> 38349 | C36: =Tab2_Core_Returns!C51 -> 37373 | D36: =Tab2_Core_Returns!D51 -> 37147 | E36: =Tab2_Core_Returns!E51 -> 42253 | F36: =Tab2_Core_Returns!F51 -> 43084 | G36: =Tab2_Core_Returns!G51 -> 46290.805 | H36: =Tab2_Core_Returns!H51 -> 47090.805 | I36: =Tab2_Core_Returns!I51 -> 47890.805 | ... K36: =Tab2_Core_Returns!K51 -> 49490.805 | L36: Link: Tab 2 (Debt + Equity – Cash)
A37: Invested capital — average | C37: =Tab2_Core_Returns!C52 -> 37861 | D37: =Tab2_Core_Returns!D52 -> 37260 | E37: =Tab2_Core_Returns!E52 -> 39700 | F37: =Tab2_Core_Returns!F52 -> 42668.5 | G37: =Tab2_Core_Returns!G52 -> 44687.403 | H37: =Tab2_Core_Returns!H52 -> 46690.805 | I37: =Tab2_Core_Returns!I52 -> 47490.805 | J37: =Tab2_Core_Returns!J52 -> 48290.805 | K37: =Tab2_Core_Returns!K52 -> 49090.805 | L37: Link: Tab 2 · FY21 blank (needs FY20 balance sheet)
A38: ROIC — on ending capital | B38: =B35/B36 -> 0.34211609 | C38: =C35/C36 -> 0.43430236 | D38: =D35/D36 -> 0.48466252 | E38: =E35/E36 -> 0.47001154 | F38: =F35/F36 -> 0.5110067 | G38: =G35/G36 -> 0.5460621 | H38: =H35/H36 -> 0.58769391 | I38: =I35/I36 -> 0.6392632 | ... K38: =K35/K36 -> 0.74306791 | L38: Formula: NOPAT / ending invested capital
A39: ROIC — on average capital (primary) | C39: =C35/C37 -> 0.42870452 | D39: =D35/D37 -> 0.48319266 | E39: =E35/E37 -> 0.50023671 | F39: =F35/F37 -> 0.51598281 | G39: =G35/G37 -> 0.56565503 | H39: =H35/H37 -> 0.59272869 | I39: =I35/I37 -> 0.64464751 | J39: =J35/J37 -> 0.69570268 | K39: =K35/K37 -> 0.74912255 | L39: Formula: NOPAT / average invested capital · preferred: matches a full year of profit to the capital employed through the year
A40: Memo: ROIC on GAAP EBIT (litigation left in) | C40: =Tab2_Core_Returns!C16*(1-C34)/C37 -> 0.40979718 | D40: =Tab2_Core_Returns!D16*(1-D34)/D37 -> 0.4627649 | E40: =Tab2_Core_Returns!E16*(1-E34)/E37 -> 0.49062997 | F40: =Tab2_Core_Returns!F16*(1-F34)/F37 -> 0.46620318 | G40: =Tab2_Core_Returns!G16*(1-G34)/G37 -> 0.54140659 | H40: =Tab2_Core_Returns!H16*(1-H34)/H37 -> 0.58384043 | I40: =Tab2_Core_Returns!I16*(1-I34)/I37 -> 0.63590898 | J40: =Tab2_Core_Returns!J16*(1-J34)/J37 -> 0.68710891 | K40: =Tab2_Core_Returns!K16*(1-K34)/K37 -> 0.74066883 | L40: Shows the litigation drag on reported returns
A41: Operating ROIC — excluding goodwill (return on the operating network)
A42: Invested capital ex-goodwill — ending | B42: =Tab2_Core_Returns!B56 -> 22391 | C42: =Tab2_Core_Returns!C56 -> 19586 | D42: =Tab2_Core_Returns!D56 -> 19150 | E42: =Tab2_Core_Returns!E56 -> 23312 | F42: =Tab2_Core_Returns!F56 -> 23205 | G42: =Tab2_Core_Returns!G56 -> 25611.805 | H42: =Tab2_Core_Returns!H56 -> 25611.805 | I42: =Tab2_Core_Returns!I56 -> 25611.805 | ... K42: =Tab2_Core_Returns!K56 -> 25611.805 | L42: Link: Tab 2 (Invested capital – Goodwill)
A43: Invested capital ex-goodwill — average | C43: =AVERAGE(B42,C42) -> 20988.5 | D43: =AVERAGE(C42,D42) -> 19368 | E43: =AVERAGE(D42,E42) -> 21231 | F43: =AVERAGE(E42,F42) -> 23258.5 | G43: =AVERAGE(F42,G42) -> 24408.403 | H43: =AVERAGE(G42,H42) -> 25611.805 | I43: =AVERAGE(H42,I42) -> 25611.805 | J43: =AVERAGE(I42,J42) -> 25611.805 | K43: =AVERAGE(J42,K42) -> 25611.805 | L43: Formula: (Opening + Closing) / 2
A44: Operating ROIC — on average capital | C44: =C35/C43 -> 0.77333692 | D44: =D35/D43 -> 0.9295621 | E44: =E35/E43 -> 0.93539624 | F44: =F35/F43 -> 0.94658781 | G44: =G35/G43 -> 1.0356128 | H44: =H35/H43 -> 1.0805556 | I44: =I35/I43 -> 1.1953406 | J44: =J35/J43 -> 1.3117405 | K44: =K35/K43 -> 1.4358624 | L44: Formula: NOPAT / average invested capital ex-goodwill
A45: Memo: Tangible invested capital (ex-goodwill & intangibles) | B45: =Tab2_Core_Returns!B57 -> -5273 | C45: =Tab2_Core_Returns!C57 -> -5479 | D45: =Tab2_Core_Returns!D57 -> -6954 | E45: =Tab2_Core_Returns!E57 -> -3577 | F45: =Tab2_Core_Returns!F57 -> -4441 | G45: =Tab2_Core_Returns!G57 -> -2034.1946 | H45: =Tab2_Core_Returns!H57 -> -2034.1946 | I45: =Tab2_Core_Returns!I57 -> -2034.1946 | ... K45: =Tab2_Core_Returns!K57 -> -2034.1946 | L45: Negative every year → ROIC on tangible capital is not meaningful (see note 1)
A46: The economic spread & value creation
A47: WACC (today's, applied to all years) | B47: =$B$26 -> 0.096744774 | C47: =$B$26 -> 0.096744774 | D47: =$B$26 -> 0.096744774 | E47: =$B$26 -> 0.096744774 | F47: =$B$26 -> 0.096744774 | G47: =$B$26 -> 0.096744774 | H47: =$B$26 -> 0.096744774 | I47: =$B$26 -> 0.096744774 | ... K47: =$B$26 -> 0.096744774 | L47: Link: WACC cell above (see note 2)
A48: ROIC spread | C48: =C39-C47 -> 0.33195975 | D48: =D39-D47 -> 0.38644789 | E48: =E39-E47 -> 0.40349194 | F48: =F39-F47 -> 0.41923804 | G48: =G39-G47 -> 0.46891026 | H48: =H39-H47 -> 0.49598391 | I48: =I39-I47 -> 0.54790274 | J48: =J39-J47 -> 0.5989579 | K48: =K39-K47 -> 0.65237778 | L48: Formula: ROIC (average capital) – WACC
A49: Operating ROIC spread | C49: =C44-C47 -> 0.67659215 | D49: =D44-D47 -> 0.83281732 | E49: =E44-E47 -> 0.83865146 | F49: =F44-F47 -> 0.84984304 | G49: =G44-G47 -> 0.93886803 | H49: =H44-H47 -> 0.98381083 | I49: =I44-I47 -> 1.0985958 | J49: =J44-J47 -> 1.2149957 | K49: =K44-K47 -> 1.3391177 | L49: Formula: Operating ROIC – WACC
A50: Economic profit ($mm) | C50: =C35-C47*C37 -> 12568.328 | D50: =D35-D47*D37 -> 14399.048 | E50: =E35-E47*E37 -> 16018.63 | F50: =F35-F47*F37 -> 17888.258 | G50: =G35-G47*G37 -> 20954.382 | H50: =H35-H47*H37 -> 23157.888 | I50: =I35-I47*I37 -> 26020.342 | J50: =J35-J47*J37 -> 28924.16 | K50: =K35-K47*K37 -> 32025.751 | L50: Formula: NOPAT – WACC × average invested capital (= spread × capital)
A51: Capital charge ($mm) | C51: =C47*C37 -> 3662.8539 | D51: =D47*D37 -> 3604.7103 | E51: =E47*E37 -> 3840.7675 | F51: =F47*F37 -> 4127.9544 | G51: =G47*G37 -> 4323.2727 | H51: =H47*H37 -> 4517.0914 | I51: =I47*I37 -> 4594.4872 | J51: =J47*J37 -> 4671.883 | K51: =K47*K37 -> 4749.2789 | L51: Formula: WACC × average invested capital — the 'rent' on investors' money
A52: Economic profit as % of NOPAT | C52: =C50/C35 -> 0.77433228 | D52: =D50/D35 -> 0.79978013 | E52: =E50/E35 -> 0.80660201 | F52: =F50/F35 -> 0.81250388 | G52: =G50/G35 -> 0.8289686 | H52: =H50/H35 -> 0.83678068 | I52: =I50/I35 -> 0.84992609 | J52: =J50/J35 -> 0.86093948 | K52: =K50/K35 -> 0.87085588 | L52: Share of after-tax operating profit that is pure value creation
A54: WACC sensitivity — beta (rows) × equity risk premium (columns); capital weights and Kd held constant
A55: Beta \ ERP | B55: 0.04 | C55: 0.045 | D55: 0.05 | E55: 0.055 | F55: 0.06 | G55: Beta used in CAPM (after any Blume adjustment): 0.59 = low · 0.77 · 0.85 ≈ base · 0.95 · 1.10 = stress
A56: 0.59 | B56: =$B$24*($B$6+$A56*B$55)+$B$25*$B$16 -> 0.074540162 | C56: =$B$24*($B$6+$A56*C$55)+$B$25*$B$16 -> 0.077397525 | D56: =$B$24*($B$6+$A56*D$55)+$B$25*$B$16 -> 0.080254887 | E56: =$B$24*($B$6+$A56*E$55)+$B$25*$B$16 -> 0.083112249 | F56: =$B$24*($B$6+$A56*F$55)+$B$25*$B$16 -> 0.085969612 | G56: Even the stress case (≈11.6%) leaves FY25 ROIC (51.6%) about 40 points above WACC.
A57: 0.77 | B57: =$B$24*($B$6+$A57*B$55)+$B$25*$B$16 -> 0.081514064 | C57: =$B$24*($B$6+$A57*C$55)+$B$25*$B$16 -> 0.085243164 | D57: =$B$24*($B$6+$A57*D$55)+$B$25*$B$16 -> 0.088972264 | E57: =$B$24*($B$6+$A57*E$55)+$B$25*$B$16 -> 0.092701364 | F57: =$B$24*($B$6+$A57*F$55)+$B$25*$B$16 -> 0.096430464
A58: 0.85 | B58: =$B$24*($B$6+$A58*B$55)+$B$25*$B$16 -> 0.084613575 | C58: =$B$24*($B$6+$A58*C$55)+$B$25*$B$16 -> 0.088730114 | D58: =$B$24*($B$6+$A58*D$55)+$B$25*$B$16 -> 0.092846653 | E58: =$B$24*($B$6+$A58*E$55)+$B$25*$B$16 -> 0.096963192 | F58: =$B$24*($B$6+$A58*F$55)+$B$25*$B$16 -> 0.10107973
A59: 0.95 | B59: =$B$24*($B$6+$A59*B$55)+$B$25*$B$16 -> 0.088487965 | C59: =$B$24*($B$6+$A59*C$55)+$B$25*$B$16 -> 0.093088803 | D59: =$B$24*($B$6+$A59*D$55)+$B$25*$B$16 -> 0.09768964 | E59: =$B$24*($B$6+$A59*E$55)+$B$25*$B$16 -> 0.10229048 | F59: =$B$24*($B$6+$A59*F$55)+$B$25*$B$16 -> 0.10689132
A60: 1.1 | B60: =$B$24*($B$6+$A60*B$55)+$B$25*$B$16 -> 0.094299549 | C60: =$B$24*($B$6+$A60*C$55)+$B$25*$B$16 -> 0.099626835 | D60: =$B$24*($B$6+$A60*D$55)+$B$25*$B$16 -> 0.10495412 | E60: =$B$24*($B$6+$A60*E$55)+$B$25*$B$16 -> 0.11028141 | F60: =$B$24*($B$6+$A60*F$55)+$B$25*$B$16 -> 0.11560869
A62: FY25 economic profit sensitivity ($mm) — same axes · = FY25 NOPAT – WACC × FY25 average invested capital
A63: Beta \ ERP | B63: =B55 -> 0.04 | C63: =C55 -> 0.045 | D63: =D55 -> 0.05 | E63: =E55 -> 0.055 | F63: =F55 -> 0.06 | G63: Formula: NOPAT – (WACC from the grid above) × average invested capital. Live: updates with every input.
A64: =A56 -> 0.59 | B64: =$F$35-B56*$F$37 -> 18835.696 | C64: =$F$35-C56*$F$37 -> 18713.776 | D64: =$F$35-D56*$F$37 -> 18591.857 | E64: =$F$35-E56*$F$37 -> 18469.938 | F64: =$F$35-F56*$F$37 -> 18348.018 | G64: Range ≈ $17.1B–$18.8B, i.e. 78–86% of FY25 NOPAT ($22.0B) is value created after the capital charge in every case.
A65: =A57 -> 0.77 | B65: =$F$35-B57*$F$37 -> 18538.13 | C65: =$F$35-C57*$F$37 -> 18379.015 | D65: =$F$35-D57*$F$37 -> 18219.9 | E65: =$F$35-E57*$F$37 -> 18060.784 | F65: =$F$35-F57*$F$37 -> 17901.669
A66: =A58 -> 0.85 | B66: =$F$35-B58*$F$37 -> 18405.878 | C66: =$F$35-C58*$F$37 -> 18230.232 | D66: =$F$35-D58*$F$37 -> 18054.585 | E66: =$F$35-E58*$F$37 -> 17878.939 | F66: =$F$35-F58*$F$37 -> 17703.292
A67: =A59 -> 0.95 | B67: =$F$35-B59*$F$37 -> 18240.564 | C67: =$F$35-C59*$F$37 -> 18044.253 | D67: =$F$35-D59*$F$37 -> 17847.942 | E67: =$F$35-E59*$F$37 -> 17651.631 | F67: =$F$35-F59*$F$37 -> 17455.321
A68: =A60 -> 1.1 | B68: =$F$35-B60*$F$37 -> 17992.592 | C68: =$F$35-C60*$F$37 -> 17765.285 | D68: =$F$35-D60*$F$37 -> 17537.978 | E68: =$F$35-E60*$F$37 -> 17310.67 | F68: =$F$35-F60*$F$37 -> 17083.363
A70: Notes
A71: 1. Tangible invested capital is negative in every year (FY25: –$4.4B): the operating network is funded by operating liabilities (client-incentive accruals, settlement obligations, deferred taxes), not shareholder capital. The return on tangible capital is therefore not meaningful — more precisely, Visa needs no net tangible capital to grow. Operating ROIC excludes goodwill only.
A72: 2. WACC uses today's market inputs (10-year yield 5.19%) for every historical year — a simplification. Rates were much lower in FY21–FY22, so historical spreads are, if anything, understated.
A73: 3. ROIC uses EBIT ex-litigation. On GAAP EBIT, FY25 ROIC falls by ~5 points, but the spread is still above 35 points.
A74: 5. Projections (FY26P–FY30P) link to Tab 2. ROIC keeps rising (to ~75% by FY30P) because NOPAT grows ~9–10% a year while invested capital grows only ~1–2% (acquisitions only — Visa returns ~95% of FCF). That is the toll-road mechanic in one line, but treat the outer years as an upper bound: share-based comp and any larger acquisition would add capital. Operating ROIC ex-goodwill exceeds 100% because acquisitions are booked to goodwill.
A75: 4. Cost of debt is a marginal market rate (traded yield on Visa's 2035 notes), not Visa's ~3% effective rate on legacy low-coupon notes. Debt is ~3% of capital, so this choice moves WACC by only a few basis points.

Sheet Tab4_Capital_Allocation
A1: Tab 4 — Capital Allocation Tracker
A2: Visa Inc. · $ in millions unless noted · FY ends Sep 30 · green = link · black = formula · blue on yellow = base-case assumption
B3: Historical (audited) | G3: Projections — base case
A4: Line item | B4: FY21 | C4: FY22 | D4: FY23 | E4: FY24 | F4: FY25 | G4: FY26P | H4: FY27P | I4: FY28P | J4: FY29P | K4: FY30P | L4: Formula / note
A6: Cash generated
A7: Free cash flow generated | B7: =Tab2_Core_Returns!B62 -> 14522 | C7: =Tab2_Core_Returns!C62 -> 17879 | D7: =Tab2_Core_Returns!D62 -> 19696 | E7: =Tab2_Core_Returns!E62 -> 18693 | F7: =Tab2_Core_Returns!F62 -> 21577 | G7: =Tab2_Core_Returns!G62 -> 21661.249 | H7: =Tab2_Core_Returns!H62 -> 27135.48 | I7: =Tab2_Core_Returns!I62 -> 30075.33 | ... K7: =Tab2_Core_Returns!K62 -> 36235.53 | L7: Link: Tab 2
A8: Net income | B8: =Tab2_Core_Returns!B28 -> 12311 | C8: =Tab2_Core_Returns!C28 -> 14957 | D8: =Tab2_Core_Returns!D28 -> 17273 | E8: =Tab2_Core_Returns!E28 -> 19743 | F8: =Tab2_Core_Returns!F28 -> 20058 | G8: =Tab2_Core_Returns!G28 -> 24068.054 | H8: =Tab2_Core_Returns!H28 -> 27135.48 | I8: =Tab2_Core_Returns!I28 -> 30075.33 | ... K8: =Tab2_Core_Returns!K28 -> 36235.53 | L8: Link: Tab 2
A10: Capital returned to shareholders
A11: Less: Dividends paid | B11: =Data!C55 -> 2798 | C11: =Data!D55 -> 3203 | D11: =Data!E55 -> 3751 | E11: =Data!F55 -> 4217 | F11: =Data!G55 -> 4634 | G11: =G8*G25 -> 5174.6317 | H11: =H8*H25 -> 5969.8055 | I11: =I8*I25 -> 6616.5725 | J11: =J8*J25 -> 7272.4394 | K11: =K8*K25 -> 7971.8165 | L11: Hist: cash flow statement · Proj: Net income × payout ratio
A12: Less: Share repurchases (buybacks) | B12: =Data!C54 -> 8676 | C12: =Data!D54 -> 11589 | D12: =Data!E54 -> 12101 | E12: =Data!F54 -> 16713 | F12: =Data!G54 -> 18316 | G12: =G7*G15-G11 -> 20818.867 | H12: =H7*H15-H11 -> 19808.9 | I12: =I7*I15-I11 -> 21954.991 | J12: =J7*J15-J11 -> 24131.276 | K12: =K7*K15-K11 -> 26451.937 | L12: Hist: cash flow statement · Proj: FCF × return ratio – dividends
A13: Total capital returned to shareholders | B13: =B11+B12 -> 11474 | C13: =C11+C12 -> 14792 | D13: =D11+D12 -> 15852 | E13: =E11+E12 -> 20930 | F13: =F11+F12 -> 22950 | G13: =G11+G12 -> 25993.499 | H13: =H11+H12 -> 25778.706 | I13: =I11+I12 -> 28571.563 | ... K13: =K11+K12 -> 34423.753 | L13: Formula: Dividends + Buybacks
A14: Net cash retained | B14: =B7-B11-B12 -> 3048 | C14: =C7-C11-C12 -> 3087 | D14: =D7-D11-D12 -> 3844 | E14: =E7-E11-E12 -> -2237 | F14: =F7-F11-F12 -> -1373 | G14: =G7-G11-G12 -> -4332.2498 | H14: =H7-H11-H12 -> 1356.774 | I14: =I7-I11-I12 -> 1503.7665 | ... K14: =K7-K11-K12 -> 1811.7765 | L14: Formula: FCF – Dividends – Buybacks
A15: Capital returned as % of FCF | B15: =B13/B7 -> 0.79011155 | C15: =C13/C7 -> 0.82733934 | D15: =D13/D7 -> 0.80483347 | E15: =E13/E7 -> 1.1196705 | F15: =F13/F7 -> 1.0636326 | G15: 1.2 | H15: 0.95 | I15: 0.95 | J15: 0.95 | K15: 0.95 | L15: FY26P 120%: 9M FY26 returns $20.3B vs FCF $15.2B (134%) · FY27P+ 95% (FY21–25 avg 93%)
A16: Cumulative capital returned as % of FCF | F16: =SUM(B13:F13)/SUM(B7:F7) -> 0.9310468 | K16: =SUM(G13:K13)/SUM(G7:K7) -> 0.98654941 | L16: FY25 column: FY21–FY25 · FY30P column: FY26P–FY30P
A17: Buybacks as % of capital returned | B17: =B12/B13 -> 0.75614433 | C17: =C12/C13 -> 0.78346403 | D17: =D12/D13 -> 0.76337371 | E17: =E12/E13 -> 0.79851887 | F17: =F12/F13 -> 0.79808279 | G17: =G12/G13 -> 0.80092593 | H17: =H12/H13 -> 0.76842105 | I17: =I12/I13 -> 0.76842105 | ... K17: =K12/K13 -> 0.76842105
A18: Memo: net change in total debt | C18: =Tab2_Core_Returns!C49-Tab2_Core_Returns!B49 -> 1473 | D18: =Tab2_Core_Returns!D49-Tab2_Core_Returns!C49 -> -1987 | E18: =Tab2_Core_Returns!E49-Tab2_Core_Returns!D49 -> 373 | F18: =Tab2_Core_Returns!F49-Tab2_Core_Returns!E49 -> 4335 | G18: =Tab2_Core_Returns!G49-Tab2_Core_Returns!F49 -> -1313 | H18: =Tab2_Core_Returns!H49-Tab2_Core_Returns!G49 -> 0 | I18: =Tab2_Core_Returns!I49-Tab2_Core_Returns!H49 -> 0 | J18: =Tab2_Core_Returns!J49-Tab2_Core_Returns!I49 -> 0 | K18: =Tab2_Core_Returns!K49-Tab2_Core_Returns!J49 -> 0
A20: Dividends
A21: Quarterly dividend rate | B21: =Data!C77 -> 0.32 | C21: =Data!D77 -> 0.375 | D21: =Data!E77 -> 0.45 | E21: =Data!F77 -> 0.52 | F21: =Data!G77 -> 0.59 | G21: =G22/4 -> 0.68009376 | H21: =H22/4 -> 0.80605642 | I21: =I22/4 -> 0.91566553 | J21: =J22/4 -> 1.0315313 | K21: =K22/4 -> 1.1589325 | L21: Hist: rate declared for the fiscal year · Proj: implied (DPS / 4). FY26 actual rate is $0.67
A22: Annual dividend per share | B22: =B21*4 -> 1.28 | C22: =C21*4 -> 1.5 | D22: =D21*4 -> 1.8 | E22: =E21*4 -> 2.08 | F22: =F21*4 -> 2.36 | G22: =G11/AVERAGE(F28,G28) -> 2.720375 | H22: =H11/AVERAGE(G28,H28) -> 3.2242257 | I22: =I11/AVERAGE(H28,I28) -> 3.6626621 | J22: =J11/AVERAGE(I28,J28) -> 4.1261254 | K22: =K11/AVERAGE(J28,K28) -> 4.63573 | L22: Hist: quarterly rate × 4 · Proj: dividends / average shares
A23: Dividend growth rate (per share) | C23: =C22/B22-1 -> 0.171875 | D23: =D22/C22-1 -> 0.2 | E23: =E22/D22-1 -> 0.15555556 | F23: =F22/E22-1 -> 0.13461538 | G23: =G22/F22-1 -> 0.15270129 | H23: =H22/G22-1 -> 0.18521366 | I23: =I22/H22-1 -> 0.13598193 | J23: =J22/I22-1 -> 0.12653727 | K23: =K22/J22-1 -> 0.12350683
A24: Dividend CAGR | F24: =(F22/B22)^(1/4)-1 -> 0.16526716 | K24: =(K22/F22)^(1/5)-1 -> 0.14456702 | L24: FY25 column: FY21–FY25 · FY30P column: FY25–FY30P
A25: Dividend payout ratio | B25: =B11/B8 -> 0.22727642 | C25: =C11/C8 -> 0.21414722 | D25: =D11/D8 -> 0.21715973 | E25: =E11/E8 -> 0.21359469 | F25: =F11/F8 -> 0.23103001 | G25: 0.215 | H25: 0.22 | I25: 0.22 | J25: 0.22 | K25: 0.22 | L25: Proj input: FY21–25 range 21.4–23.1% · FY26P 21.5% (FY26 rate $0.67 × 4 × ~1.9B shares ≈ $5.1B)
A27: Buybacks & share count
A28: As-converted shares outstanding at FY-end (millions) | B28: =Data!C76 -> 2161 | C28: =Data!D76 -> 2103 | D28: =Data!E76 -> 2047 | E28: =Data!F76 -> 1983 | F28: =Data!G76 -> 1930 | G28: =F28-G12/G35 -> 1874.3517 | H28: =G28-H12/H35 -> 1828.7424 | I28: =H28-I12/I35 -> 1784.243 | J28: =I28-J12/J35 -> 1740.8265 | K28: =J28-K12/K35 -> 1698.4664 | L28: Proj: prior – buybacks / share price (ignores escrow conversion-rate cuts and dilution)
A29: Change in share count | C29: =C28/B28-1 -> -0.026839426 | D29: =D28/C28-1 -> -0.026628626 | E29: =E28/D28-1 -> -0.031265266 | F29: =F28/E28-1 -> -0.026727181 | G29: =G28/F28-1 -> -0.028833333 | H29: =H28/G28-1 -> -0.024333333 | I29: =I28/H28-1 -> -0.024333333 | J29: =J28/I28-1 -> -0.024333333 | K29: =K28/J28-1 -> -0.024333333
A30: Cumulative share count reduction | F30: =F28/B28-1 -> -0.10689496 | K30: =K28/F28-1 -> -0.11996562 | L30: FY25 column: FY21–FY25 · FY30P column: FY25–FY30P
A31: Buybacks as % of net income | B31: =B12/B8 -> 0.7047356 | C31: =C12/C8 -> 0.77482115 | D31: =D12/D8 -> 0.70057315 | E31: =E12/E8 -> 0.84652788 | F31: =F12/F8 -> 0.91315186 | G31: =G12/G8 -> 0.865 | H31: =H12/H8 -> 0.73 | I31: =I12/I8 -> 0.73 | ... K31: =K12/K8 -> 0.73
A33: Shareholder yield (at fiscal year-end market value)
A34: P/E at FY-end | B34: =B36/B8 -> 39.100215 | C34: =C36/C8 -> 24.978134 | D34: =D36/D8 -> 27.258176 | E34: =E36/E8 -> 27.61616 | F34: =F36/F8 -> 32.847911 | G34: 30 | H34: 30 | I34: 30 | J34: 30 | K34: 30 | L34: Proj input: 30x (FY21–25 range 25–39x; FY25 32.8x) · sets the buyback price, not a valuation call
A35: Share price at FY-end | B35: =Data!C75 -> 222.75 | C35: =Data!D75 -> 177.65 | D35: =Data!E75 -> 230.01 | E35: =Data!F75 -> 274.95 | F35: =Data!G75 -> 341.38 | G35: =G34*G8/F28 -> 374.11483 | H35: =H34*H8/G28 -> 434.31785 | I35: =I34*I8/H28 -> 493.37724 | J35: =J34*J8/I28 -> 555.80784 | K35: =K34*K8/J28 -> 624.45391 | L35: Hist: Yahoo Close (verified) · Proj: P/E × net income / opening shares
A36: Total market capitalisation | B36: =B35*B28 -> 481362.75 | C36: =C35*C28 -> 373597.95 | D36: =D35*D28 -> 470830.47 | E36: =E35*E28 -> 545225.85 | F36: =F35*F28 -> 658863.4 | G36: =G35*G28 -> 701222.76 | H36: =H35*H28 -> 794255.49 | I36: =I35*I28 -> 880304.9 | ... K36: =K35*K28 -> 1060613.9 | L36: Formula: FY-end price × as-converted shares
A37: Dividend yield (cash paid) | B37: =B11/B36 -> 0.0058126641 | C37: =C11/C36 -> 0.0085733875 | D37: =D11/D36 -> 0.0079667741 | E37: =E11/E36 -> 0.0077344095 | F37: =F11/F36 -> 0.0070333244 | G37: =G11/G36 -> 0.0073794405 | H37: =H11/H36 -> 0.0075162282 | I37: =I11/I36 -> 0.0075162282 | ... K37: =K11/K36 -> 0.0075162282
A38: Buyback yield | B38: =B12/B36 -> 0.018023829 | C38: =C12/C36 -> 0.031019977 | D38: =D12/D36 -> 0.025701395 | E38: =E12/E36 -> 0.030653352 | F38: =F12/F36 -> 0.027799389 | G38: =G12/G36 -> 0.029689377 | H38: =H12/H36 -> 0.024940212 | I38: =I12/I36 -> 0.024940212 | ... K38: =K12/K36 -> 0.024940212
A39: Shareholder yield | B39: =B13/B36 -> 0.023836493 | C39: =C13/C36 -> 0.039593365 | D39: =D13/D36 -> 0.033668169 | E39: =E13/E36 -> 0.038387762 | F39: =F13/F36 -> 0.034832713 | G39: =G13/G36 -> 0.037068818 | H39: =H13/H36 -> 0.03245644 | I39: =I13/I36 -> 0.03245644 | ... K39: =K13/K36 -> 0.03245644 | L39: Formula: Total capital returned / Total market capitalisation
A40: FCF yield | B40: =B7/B36 -> 0.030168516 | C40: =C7/C36 -> 0.047856258 | D40: =D7/D36 -> 0.041832467 | E40: =E7/E36 -> 0.034284875 | F40: =F7/F36 -> 0.032748822 | G40: =G7/G36 -> 0.030890681 | H40: =H7/H36 -> 0.034164674 | I40: =I7/I36 -> 0.034164674 | ... K40: =K7/K36 -> 0.034164674
A42: Notes
A43: 1. Over FY21–FY25 Visa returned ~93% of its FCF to shareholders, ~78% of it through buybacks, while CapEx stayed at ~3–4% of revenue. Nothing is hoarded and no large projects absorb the cash.
A44: 2. Part of the fall in as-converted shares is not buybacks: each U.S. litigation-escrow deposit cuts the class B → A conversion rate, retiring as-converted shares at the legacy bank holders' expense.
A45: 3. In FY24 and FY25 Visa returned more than it generated (112% and 106% of FCF): FY24 funded by drawing down cash, FY25 by ~$4.3B of new debt. FY26 is running even higher (9M: 134%). The base case returns to 95% from FY27P.
A46: 4. Payout ratio uses GAAP net income; litigation provisions depress net income and lift the ratio slightly.
A47: 5. Projected share price = P/E assumption × net income / opening shares. It only sets how many shares buybacks retire — it is not a price target.

Sheet Tab5_Peer_Mastercard
A1: Tab 5 — Peer Spread: Visa vs Mastercard
A2: Mastercard rebuilt with the SAME definitions as Tabs 1–4 · $ in millions · MA fiscal year = calendar year (3-month offset to Visa) · green = link · black = formula
A4: Mastercard — line item | B4: FY21 | C4: FY22 | D4: FY23 | E4: FY24 | F4: FY25 | G4: Formula / note
A6: Volume & revenue
A7: Purchase volume ($ billions) | B7: =Data_MA!C9 -> 5974 | C7: =Data_MA!D9 -> 6571 | D7: =Data_MA!E9 -> 7345 | E7: =Data_MA!F9 -> 8003 | F7: =Data_MA!G9 -> 8799 | G7: Comparable to Visa payments volume (both exclude cash)
A8: Net revenue | B8: =Data_MA!C12 -> 18884 | C8: =Data_MA!D12 -> 22237 | D8: =Data_MA!E12 -> 25098 | E8: =Data_MA!F12 -> 28167 | F8: =Data_MA!G12 -> 32791
A9: Net revenue growth | C9: =C8/B8-1 -> 0.17755772 | D9: =D8/C8-1 -> 0.12865944 | E9: =E8/D8-1 -> 0.12228066 | F9: =F8/E8-1 -> 0.16416374
A10: Take rate (bps of purchase volume) | B10: =B8/(B7*1000)*10000 -> 31.610311 | C10: =C8/(C7*1000)*10000 -> 33.84112 | D10: =D8/(D7*1000)*10000 -> 34.170184 | E10: =E8/(E7*1000)*10000 -> 35.195552 | F10: =F8/(F7*1000)*10000 -> 37.266735 | G10: Formula: Net revenue / purchase volume · same construction as Visa's core take rate
A12: Profitability
A13: Operating income (EBIT) — GAAP | B13: =Data_MA!C15 -> 10082 | C13: =Data_MA!D15 -> 12264 | D13: =Data_MA!E15 -> 14008 | E13: =Data_MA!F15 -> 15582 | F13: =Data_MA!G15 -> 18897
A14: Operating margin — GAAP | B14: =B13/B8 -> 0.53389112 | C14: =C13/C8 -> 0.55151324 | D14: =D13/D8 -> 0.55813212 | E14: =E13/E8 -> 0.55320055 | F14: =F13/F8 -> 0.57628618
A15: Add back: Provision for litigation | B15: =Data_MA!C14 -> 94 | C15: =Data_MA!D14 -> 356 | D15: =Data_MA!E14 -> 539 | E15: =Data_MA!F14 -> 680 | F15: =Data_MA!G14 -> 504
A16: EBIT ex-litigation | B16: =B13+B15 -> 10176 | C16: =C13+C15 -> 12620 | D16: =D13+D15 -> 14547 | E16: =E13+E15 -> 16262 | F16: =F13+F15 -> 19401 | G16: Same treatment as Visa (Tab 2)
A17: Operating margin — ex-litigation | B17: =B16/B8 -> 0.53886888 | C17: =C16/C8 -> 0.5675226 | D17: =D16/D8 -> 0.57960794 | E17: =E16/E8 -> 0.57734228 | F17: =F16/F8 -> 0.59165625
A18: Tax rate — GAAP effective | B18: =Data_MA!C16/Data_MA!C18 -> 0.15717474 | C18: =Data_MA!D16/Data_MA!D18 -> 0.153597 | D18: =Data_MA!E16/Data_MA!E18 -> 0.17919202 | E18: =Data_MA!F16/Data_MA!F18 -> 0.15602465 | F18: =Data_MA!G16/Data_MA!G18 -> 0.19431586 | G18: FY25 19.4% vs 15.6% in FY24 (4Q25 release)
A19: Net income | B19: =Data_MA!C17 -> 8687 | C19: =Data_MA!D17 -> 9930 | D19: =Data_MA!E17 -> 11195 | E19: =Data_MA!F17 -> 12874 | F19: =Data_MA!G17 -> 14968
A20: Net margin | B20: =B19/B8 -> 0.46001906 | C20: =C19/C8 -> 0.44655304 | D20: =D19/D8 -> 0.44605148 | E20: =E19/E8 -> 0.45705968 | F20: =F19/F8 -> 0.45646671
A22: Returns on capital
A23: NOPAT | B23: =B16*(1-B18) -> 8576.5899 | C23: =C16*(1-C18) -> 10681.606 | D23: =D16*(1-D18) -> 11940.294 | E23: =E16*(1-E18) -> 13724.727 | F23: =F16*(1-F18) -> 15631.078 | G23: Formula: EBIT ex-litigation × (1 – tax rate)
A24: Total debt | B24: =Data_MA!C26+Data_MA!C27 -> 13901 | C24: =Data_MA!D26+Data_MA!D27 -> 14023 | D24: =Data_MA!E26+Data_MA!E27 -> 15681 | E24: =Data_MA!F26+Data_MA!F27 -> 18226 | F24: =Data_MA!G26+Data_MA!G27 -> 19000
A25: Total equity | B25: =Data_MA!C28 -> 7383 | C25: =Data_MA!D28 -> 6356 | D25: =Data_MA!E28 -> 6975 | E25: =Data_MA!F28 -> 6515 | F25: =Data_MA!G28 -> 7746
A26: Cash + investments deducted | B26: =Data_MA!C21+Data_MA!C23 -> 7894 | C26: =Data_MA!D21+Data_MA!D23 -> 7408 | D26: =Data_MA!E21+Data_MA!E23 -> 9180 | E26: =Data_MA!F21+Data_MA!F23 -> 8772 | F26: =Data_MA!G21+Data_MA!G23 -> 10898 | G26: Restricted litigation cash not deducted (as for Visa's escrow)
A27: Invested capital | B27: =B24+B25-B26 -> 13390 | C27: =C24+C25-C26 -> 12971 | D27: =D24+D25-D26 -> 13476 | E27: =E24+E25-E26 -> 15969 | F27: =F24+F25-F26 -> 15848 | G27: Formula: Debt + Equity – Cash (Tab 2 definition)
A28: Average invested capital | C28: =AVERAGE(B27,C27) -> 13180.5 | D28: =AVERAGE(C27,D27) -> 13223.5 | E28: =AVERAGE(D27,E27) -> 14722.5 | F28: =AVERAGE(E27,F27) -> 15908.5
A29: ROIC — on average capital | C29: =C23/C28 -> 0.81040976 | D29: =D23/D28 -> 0.90296016 | E29: =E23/E28 -> 0.93222803 | F29: =F23/F28 -> 0.9825614
A30: Goodwill | B30: =Data_MA!C24 -> 7662 | C30: =Data_MA!D24 -> 7522 | D30: =Data_MA!E24 -> 7660 | E30: =Data_MA!F24 -> 9193 | F30: =Data_MA!G24 -> 9560
A31: Other intangible assets, net | B31: =Data_MA!C25 -> 3671 | C31: =Data_MA!D25 -> 3859 | D31: =Data_MA!E25 -> 4086 | E31: =Data_MA!F25 -> 5453 | F31: =Data_MA!G25 -> 5554
A32: Invested capital ex-goodwill | B32: =B27-B30 -> 5728 | C32: =C27-C30 -> 5449 | D32: =D27-D30 -> 5816 | E32: =E27-E30 -> 6776 | F32: =F27-F30 -> 6288
A33: Operating ROIC — ex-goodwill (average) | C33: =C23/AVERAGE(B32,C32) -> 1.9113547 | D33: =D23/AVERAGE(C32,D32) -> 2.1198923 | E33: =E23/AVERAGE(D32,E32) -> 2.1799122 | F33: =F23/AVERAGE(E32,F32) -> 2.3930003
A34: Memo: Tangible invested capital | B34: =B32-B31 -> 2057 | C34: =C32-C31 -> 1590 | D34: =D32-D31 -> 1730 | E34: =E32-E31 -> 1323 | F34: =F32-F31 -> 734 | G34: Small but positive for MA; negative for Visa
A36: Cash flow & capital allocation
A37: CapEx (PP&E + capitalized software) | B37: =Data_MA!C32+Data_MA!C33 -> 814 | C37: =Data_MA!D32+Data_MA!D33 -> 1097 | D37: =Data_MA!E32+Data_MA!E33 -> 1088 | E37: =Data_MA!F32+Data_MA!F33 -> 1194 | F37: =Data_MA!G32+Data_MA!G33 -> 1215 | G37: Both lines, to match Visa's 'property, equipment and technology'
A38: Free cash flow | B38: =Data_MA!C31-B37 -> 8649 | C38: =Data_MA!D31-C37 -> 10098 | D38: =Data_MA!E31-D37 -> 10892 | E38: =Data_MA!F31-E37 -> 13586 | F38: =Data_MA!G31-F37 -> 16433 | G38: Formula: OCF – CapEx
A39: FCF conversion (FCF / net income) | B39: =B38/B19 -> 0.99562565 | C39: =C38/C19 -> 1.0169184 | D39: =D38/D19 -> 0.97293435 | E39: =E38/E19 -> 1.0553053 | F39: =F38/F19 -> 1.0978755
A40: Capital intensity (CapEx / net revenue) | B40: =B37/B8 -> 0.043105274 | C40: =C37/C8 -> 0.049332194 | D40: =D37/D8 -> 0.043350068 | E40: =E37/E8 -> 0.042390031 | F40: =F37/F8 -> 0.03705285
A41: Capital returned (dividends + buybacks) | B41: =Data_MA!C36+Data_MA!C35 -> 7645 | C41: =Data_MA!D36+Data_MA!D35 -> 10656 | D41: =Data_MA!E36+Data_MA!E35 -> 11190 | E41: =Data_MA!F36+Data_MA!F35 -> 13402 | F41: =Data_MA!G36+Data_MA!G35 -> 14483
A42: Capital returned as % of FCF | B42: =B41/B38 -> 0.88391722 | C42: =C41/C38 -> 1.0552585 | D42: =D41/D38 -> 1.0273595 | E42: =E41/E38 -> 0.98645665 | F42: =F41/F38 -> 0.88133634
A43: Dividend payout ratio | B43: =Data_MA!C36/B19 -> 0.20041441 | C43: =Data_MA!D36/C19 -> 0.19164149 | D43: =Data_MA!E36/D19 -> 0.19276463 | E43: =Data_MA!F36/E19 -> 0.19015069 | F43: =Data_MA!G36/F19 -> 0.18412614
A44: Acquisitions (cash) | B44: =Data_MA!C34 -> 4436 | C44: =Data_MA!D34 -> 313 | D44: =Data_MA!E34 -> 0 | E44: =Data_MA!F34 -> 2511 | F44: =Data_MA!G34 -> 0 | G44: Lumpy: FY21 $4.4B and FY24 $2.5B (e.g. Recorded Future)
A46: Mastercard WACC (same market inputs as Tab 3)
A47: Risk-free rate | B47: =Tab3_ROIC_WACC!B6 -> 0.0519 | G47: Link: Tab 3
A48: Equity risk premium | B48: =Tab3_ROIC_WACC!B10 -> 0.055 | G48: Link: Tab 3
A49: Raw beta | B49: =Data_MA!G41 -> 0.76 | G49: Data_MA (placeholder)
A50: Adjusted beta | B50: =Tab3_ROIC_WACC!B8*B49+(1-Tab3_ROIC_WACC!B8) -> 0.8392 | G50: Blume-adjusted, as for Visa
A51: Cost of equity | B51: =B47+B50*B48 -> 0.098056 | G51: Rf + β × ERP
A52: After-tax cost of debt | B52: =Tab3_ROIC_WACC!B14*(1-F18) -> 0.043668081 | G52: Assumes MA borrows at Visa's market yield (both high-grade); × (1 – MA FY25 tax rate)
A53: Market capitalisation | B53: =Data_MA!G40*Data_MA!G39 -> 528438.24 | G53: Price × shares (Data_MA)
A54: Total debt (Jun 30, 2026) | B54: =Data_MA!G42 -> 24643 | G54: Data_MA
A55: Equity weight | B55: =B53/(B53+B54) -> 0.95544416
A56: Mastercard WACC | B56: =B55*B51+(1-B55)*B52 -> 0.0956327 | G56: Formula: E-weight × Ke + D-weight × Kd
A58: FY25 head-to-head | B58: Visa | C58: Mastercard | D58: Visa – MA | G58: Why the difference matters
A59: Net revenue ($mm) | B59: =Tab2_Core_Returns!F11 -> 40000 | C59: =F8 -> 32791 | D59: =B59-C59 -> 7209 | G59: Visa is ~1.2x Mastercard's revenue
A60: Net revenue CAGR FY21–FY25 | B60: =(Tab2_Core_Returns!F11/Tab2_Core_Returns!B11)^(1/4)-1 -> 0.13498001 | C60: =(F8/B8)^(1/4)-1 -> 0.14792937 | D60: =(B60-C60)*100 -> -1.2949356 | G60: MA grew faster, helped by value-added services and cross-border recovery
A61: Volume ($ billions): Visa payments vs MA purchase | B61: =Tab1_Drivers!F7 -> 14200 | C61: =F7 -> 8799 | D61: =B61-C61 -> 5401 | G61: Visa's network is ~1.6x larger by volume
A62: Take rate (bps) | B62: =Tab1_Drivers!F36 -> 28.169014 | C62: =F10 -> 37.266735 | D62: =B62-C62 -> -9.0977208 | G62: MA earns MORE per dollar: higher value-added-services mix and more cross-border; Visa's scale is in debit
A63: Operating margin — GAAP | B63: =Tab2_Core_Returns!F17 -> 0.59985 | C63: =F14 -> 0.57628618 | D63: =(B63-C63)*100 -> 2.3563824
A64: Operating margin — ex-litigation | B64: =Tab2_Core_Returns!F20 -> 0.6639 | C64: =F17 -> 0.59165625 | D64: =(B64-C64)*100 -> 7.2243753 | G64: Visa is ~7 pts more profitable per revenue dollar — scale economics of the larger network
A65: Net margin | B65: =Tab2_Core_Returns!F29 -> 0.50145 | C65: =F20 -> 0.45646671 | D65: =(B65-C65)*100 -> 4.4983287
A66: Invested capital ($mm) | B66: =Tab2_Core_Returns!F51 -> 43084 | C66: =F27 -> 15848 | D66: =B66-C66 -> 27236 | G66: Visa carries ~2.7x the capital — mostly Visa Europe goodwill & intangibles
A67: Goodwill + intangibles ($mm) | B67: =Tab2_Core_Returns!F54+Tab2_Core_Returns!F55 -> 47525 | C67: =F30+F31 -> 15114 | D67: =B67-C67 -> 32411 | G67: $47.5B vs $15.1B: the 2016 Visa Europe acquisition (~$23B) is the single biggest gap
A68: ROIC — average capital | B68: =Tab3_ROIC_WACC!F39 -> 0.51598281 | C68: =F29 -> 0.9825614 | D68: =(B68-C68)*100 -> -46.657859 | G68: MA's ROIC is ~2x Visa's. The gap is goodwill & intangibles ($47.5B vs $15.1B). Debt-funded buybacks do NOT explain it: they swap equity for debt, leaving debt + equity – cash unchanged
A69: Operating ROIC — ex-goodwill | B69: =Tab3_ROIC_WACC!F44 -> 0.94658781 | C69: =F33 -> 2.3930003 | D69: =(B69-C69)*100 -> -144.64125 | G69: Both are effectively capital-free networks once acquisition goodwill is removed
A70: Tangible invested capital ($mm) | B70: =Tab2_Core_Returns!F57 -> -4441 | C70: =F34 -> 734 | D70: =B70-C70 -> -5175 | G70: Both near zero or negative — neither network needs net tangible capital
A71: WACC | B71: =Tab3_ROIC_WACC!B26 -> 0.096744774 | C71: =B56 -> 0.0956327 | D71: =(B71-C71)*100 -> 0.11120731 | G71: Near-identical: same market inputs and almost the same beta (0.77 vs 0.76)
A72: ROIC – WACC spread | B72: =Tab3_ROIC_WACC!F48 -> 0.41923804 | C72: =F29-B56 -> 0.8869287 | D72: =(B72-C72)*100 -> -46.769066 | G72: Both spreads are enormous; the gap is about capital base, not moat quality
A73: Economic profit ($mm) | B73: =Tab3_ROIC_WACC!F50 -> 17888.258 | C73: =F23-B56*F28 -> 14109.705 | D73: =B73-C73 -> 3778.553 | G73: Visa still creates MORE absolute value: bigger profit pool outweighs its larger capital charge
A74: FCF conversion | B74: =Tab2_Core_Returns!F64 -> 1.0757304 | C74: =F39 -> 1.0978755 | D74: =(B74-C74)*100 -> -2.2145086
A75: Capital intensity | B75: =Tab2_Core_Returns!F65 -> 0.03705 | C75: =F40 -> 0.03705285 | D75: =(B75-C75)*100 -> -0.00028498673 | G75: Both under 4% of revenue
A76: Capital returned, % of FCF (FY21–25 cumulative) | B76: =Tab4_Capital_Allocation!F16 -> 0.9310468 | C76: =SUM(B41:F41)/SUM(B38:F38) -> 0.96174863 | D76: =(B76-C76)*100 -> -3.0701831 | G76: Both return ~all FCF; MA's equity is only ~$7.7B because buybacks have run ahead of retained earnings for years
A77: Dividend payout ratio | B77: =Tab4_Capital_Allocation!F25 -> 0.23103001 | C77: =F43 -> 0.18412614 | D77: =(B77-C77)*100 -> 4.6903877 | G77: Similar ~20% dividend policies; buybacks do the rest
A78: Market cap today ($mm) | B78: =Tab3_ROIC_WACC!B21 -> 735888.4 | C78: =B53 -> 528438.24 | D78: =B78-C78 -> 207450.16 | G78: Both at the Oct 14, 2026 close
A79: P/E on FY25 net income | B79: =Tab3_ROIC_WACC!B21/Tab2_Core_Returns!F28 -> 36.688025 | C79: =B53/F19 -> 35.304532 | D79: =B79-C79 -> 1.3834924 | G79: The market prices the two almost identically despite MA's 2x ROIC — consistent with the ROIC gap being acquisition accounting, not economics. (MA FY25 = calendar 2025, 3 months more recent)
A81: Notes
A82: 1. Same definitions as Visa: EBIT ex-litigation, GAAP effective tax, invested capital = debt + equity – (cash + investments), restricted litigation cash not deducted, CapEx includes capitalised software.
A83: 2. Timing: Mastercard FY25 = calendar 2025; Visa FY25 = Oct 2024–Sep 2025. A 3-month offset — fine for a ratio comparison, but note it if asked.
A84: 3. The headline: Mastercard's ROIC is roughly double Visa's, but this is an acquisition-accounting story, not a moat-quality story. (Careful: ROIC including goodwill is still the right measure of the return on the ~$23B Visa actually paid for Visa Europe — the goodwill is real money, not an artifact.) Visa is more profitable per revenue dollar and generates more economic profit in absolute dollars; its ROIC is diluted by ~$47B of Visa Europe goodwill and intangibles. Strip goodwill out and both networks need essentially no tangible capital.
A85: 4. Mastercard's low equity (~$7.7B) reflects years of debt-funded buybacks — it inflates ROE far more than ROIC, which is why ROIC (debt + equity) is the fairer comparison.
A86: 5. Mastercard's beta (0.76) is a third-party Yahoo figure, as is Visa's. It affects only MA's WACC, not the ROIC comparison.

Sheet Data
A1: Visa Inc. (NYSE: V) — Historical Database, FY21–FY25
A2: $ in millions unless noted · Fiscal year ends September 30 · Single source of truth: Tabs 1–4 link here, no hardcodes elsewhere
A3: Legend: blue = hardcoded from filings · black = formula · yellow = verify before final · outflows / contra-revenue stored as positive amounts (labelled 'Less:')
A5: Line item | B5: Unit | C5: FY21 | D5: FY22 | E5: FY23 | F5: FY24 | G5: FY25 | H5: Source
A7: Operational volume
A8: Payments volume | B8: $ billions | C8: 10400 | D8: 11600 | E8: 12300 | F8: 13200 | G8: 14200 | H8: FY23–25: Visa FY2025 Annual Report, key statistics: https://annualreport.visa.com/financials | FY21–22: secondary source (FourWeekMBA), but consistent with Visa's reported nominal growth: FY22 +12% (Q4 FY22 release) and FY21 +18% (Q4 FY21 release, implying FY20 ≈ $8.8T). Cross-check against the FY22 Annual Report key statistics if available.
A9: Processed transactions | B9: billions | C9: 164.7 | D9: 192.5 | E9: 212.6 | F9: 233.8 | G9: 257.5 | H9: FY21: Q4 FY21 release · FY22: Q4 FY22 release · FY23–25: FY25 Annual Report key statistics
A11: Revenue ($ millions)
A12: Service revenue | B12: $mm | C12: 11475 | D12: 13361 | E12: 14826 | F12: 16114 | G12: 17539 | H12: FY21: Q4 FY2021 earnings release (8-K Ex. 99.1): https://www.sec.gov/Archives/edgar/data/1403161/000140316121000056/q42021earningsrelease.htm · FY22–24: FY2024 10-K XBRL revenue note (R34): https://www.sec.gov/Archives/edgar/data/1403161/000140316124000058/R34.htm · FY25: Q4 FY2025 earnings release (8-K Ex. 99.1): https://www.sec.gov/Archives/edgar/data/1403161/000140316125000077/q42025earningsrelease.htm
A13: Data processing revenue | B13: $mm | C13: 12792 | D13: 14438 | E13: 16007 | F13: 17714 | G13: 19993 | H13: Same as service revenue
A14: International transaction revenue | B14: $mm | C14: 6530 | D14: 9815 | E14: 11638 | F14: 12665 | G14: 14166 | H14: Same as service revenue
A15: Other revenue | B15: $mm | C15: 1675 | D15: 1991 | E15: 2479 | F15: 3197 | G15: 4053 | H15: Same as service revenue
A16: Less: Client incentives | B16: $mm | C16: 8367 | D16: 10295 | E16: 12297 | F16: 13764 | G16: 15751 | H16: Same as service revenue; FY21–25 also tie to 5-yr XBRL extract of 10-K filings (edgar.tools): https://app.edgar.tools/companies/V
A17: Net revenue (as reported) | B17: $mm | C17: 24105 | D17: 29310 | E17: 32653 | F17: 35926 | G17: 40000 | H17: 5-yr XBRL extract of 10-K filings (edgar.tools): https://app.edgar.tools/companies/V
A19: Operating expenses ($ millions)
A20: Personnel | B20: $mm | C20: 4240 | D20: 4990 | E20: 5831 | F20: 6264 | G20: 6961 | H20: 5-yr XBRL extract of 10-K filings (edgar.tools): https://app.edgar.tools/companies/V · FY23–25 also Visa FY2025 Form 10-K (filed 2025-11-06): https://www.sec.gov/Archives/edgar/data/1403161/000140316125000089/v-20250930.htm
A21: Marketing | B21: $mm | C21: 1136 | D21: 1336 | E21: 1341 | F21: 1560 | G21: 1684 | H21: 5-yr XBRL extract of 10-K filings (edgar.tools): https://app.edgar.tools/companies/V · FY23–25 also Visa FY2025 Form 10-K (filed 2025-11-06): https://www.sec.gov/Archives/edgar/data/1403161/000140316125000089/v-20250930.htm
A22: Network and processing | B22: $mm | C22: 730 | D22: 743 | E22: 736 | F22: 778 | G22: 894 | H22: 5-yr XBRL extract of 10-K filings (edgar.tools): https://app.edgar.tools/companies/V · FY23–25 also Visa FY2025 Form 10-K (filed 2025-11-06): https://www.sec.gov/Archives/edgar/data/1403161/000140316125000089/v-20250930.htm
A23: Professional fees | B23: $mm | C23: 403 | D23: 505 | E23: 545 | F23: 635 | G23: 759 | H23: 5-yr XBRL extract of 10-K filings (edgar.tools): https://app.edgar.tools/companies/V · FY23–25 also Visa FY2025 Form 10-K (filed 2025-11-06): https://www.sec.gov/Archives/edgar/data/1403161/000140316125000089/v-20250930.htm
A24: Depreciation and amortization | B24: $mm | C24: 804 | D24: 861 | E24: 943 | F24: 1034 | G24: 1220 | H24: 5-yr XBRL extract of 10-K filings (edgar.tools): https://app.edgar.tools/companies/V · FY23–25 also Visa FY2025 Form 10-K (filed 2025-11-06): https://www.sec.gov/Archives/edgar/data/1403161/000140316125000089/v-20250930.htm
A25: General and administrative | B25: $mm | C25: 985 | D25: 1194 | E25: 1330 | F25: 1598 | G25: 1926 | H25: 5-yr XBRL extract of 10-K filings (edgar.tools): https://app.edgar.tools/companies/V · FY23–25 also Visa FY2025 Form 10-K (filed 2025-11-06): https://www.sec.gov/Archives/edgar/data/1403161/000140316125000089/v-20250930.htm
A26: Litigation provision | B26: $mm | C26: 3 | D26: 868 | E26: 927 | F26: 462 | G26: 2562 | H26: 5-yr XBRL extract of 10-K filings (edgar.tools): https://app.edgar.tools/companies/V · FY23–25 also Visa FY2025 Form 10-K (filed 2025-11-06): https://www.sec.gov/Archives/edgar/data/1403161/000140316125000089/v-20250930.htm
A27: Total operating expenses (as reported) | B27: $mm | C27: 8301 | D27: 10497 | E27: 11653 | F27: 12331 | G27: 16006 | H27: 5-yr XBRL extract of 10-K filings (edgar.tools): https://app.edgar.tools/companies/V
A28: Memo: Visa non-GAAP operating expenses | B28: $mm | C28: 8077 | D28: 9387 | E28: 10481 | F28: 11609 | G28: 12906 | H28: FY21: Q4 FY21 release · FY22: Q4 FY22 release · FY23–25: Visa FY2025 Annual Report, key statistics: https://annualreport.visa.com/financials
A30: Income statement ($ millions)
A31: Operating income (as reported) | B31: $mm | C31: 15804 | D31: 18813 | E31: 21000 | F31: 23595 | G31: 23994 | H31: 5-yr XBRL extract of 10-K filings (edgar.tools): https://app.edgar.tools/companies/V
A32: Interest expense | B32: $mm | C32: 513 | D32: 538 | E32: 644 | F32: 641 | G32: 589 | H32: FY21: Q4 FY21 release · FY22–25: 5-yr XBRL extract of 10-K filings (edgar.tools): https://app.edgar.tools/companies/V
A33: Total non-operating income (expense) | B33: $mm | C33: 259 | D33: -677 | E33: 37 | F33: 321 | G33: 200 | H33: 5-yr XBRL extract of 10-K filings (edgar.tools): https://app.edgar.tools/companies/V
A34: Income before income taxes | B34: $mm | C34: 16063 | D34: 18136 | E34: 21037 | F34: 23916 | G34: 24194 | H34: 5-yr XBRL extract of 10-K filings (edgar.tools): https://app.edgar.tools/companies/V
A35: Income tax provision | B35: $mm | C35: 3752 | D35: 3179 | E35: 3764 | F35: 4173 | G35: 4136 | H35: 5-yr XBRL extract of 10-K filings (edgar.tools): https://app.edgar.tools/companies/V
A36: Net income | B36: $mm | C36: 12311 | D36: 14957 | E36: 17273 | F36: 19743 | G36: 20058 | H36: 5-yr XBRL extract of 10-K filings (edgar.tools): https://app.edgar.tools/companies/V
A38: Balance sheet at Sep 30 ($ millions)
A39: Cash and cash equivalents | B39: $mm | C39: 16487 | D39: 15689 | E39: 16286 | F39: 11975 | G39: 17164 | H39: 5-yr XBRL extract of 10-K filings (edgar.tools): https://app.edgar.tools/companies/V · FY24–25 also Q4 FY2025 earnings release (8-K Ex. 99.1): https://www.sec.gov/Archives/edgar/data/1403161/000140316125000077/q42025earningsrelease.htm
A40: Restricted cash equivalents — U.S. litigation escrow | B40: $mm | C40: 894 | D40: 1449 | E40: 1764 | F40: 3089 | G40: 2990 | H40: 5-yr XBRL extract of 10-K filings (edgar.tools): https://app.edgar.tools/companies/V · FY24–25 also Q4 FY2025 earnings release (8-K Ex. 99.1): https://www.sec.gov/Archives/edgar/data/1403161/000140316125000077/q42025earningsrelease.htm
A41: Investment securities — current | B41: $mm | C41: 2025 | D41: 2833 | E41: 3842 | F41: 3200 | G41: 1833 | H41: 5-yr XBRL extract of 10-K filings (edgar.tools): https://app.edgar.tools/companies/V · FY24–25 also Q4 FY2025 earnings release (8-K Ex. 99.1): https://www.sec.gov/Archives/edgar/data/1403161/000140316125000077/q42025earningsrelease.htm
A42: Investment securities — non-current | B42: $mm | C42: 1705 | D42: 2136 | E42: 1921 | F42: 2545 | G42: 999 | H42: 5-yr XBRL extract of 10-K filings (edgar.tools): https://app.edgar.tools/companies/V · FY24–25 also Q4 FY2025 earnings release (8-K Ex. 99.1): https://www.sec.gov/Archives/edgar/data/1403161/000140316125000077/q42025earningsrelease.htm
A43: Goodwill | B43: $mm | C43: 15958 | D43: 17787 | E43: 17997 | F43: 18941 | G43: 19879 | H43: 5-yr XBRL extract of 10-K filings (edgar.tools): https://app.edgar.tools/companies/V · FY24–25 also Q4 FY2025 earnings release (8-K Ex. 99.1): https://www.sec.gov/Archives/edgar/data/1403161/000140316125000077/q42025earningsrelease.htm
A44: Intangible assets, net | B44: $mm | C44: 27664 | D44: 25065 | E44: 26104 | F44: 26889 | G44: 27646 | H44: 5-yr XBRL extract of 10-K filings (edgar.tools): https://app.edgar.tools/companies/V · FY24–25 also Q4 FY2025 earnings release (8-K Ex. 99.1): https://www.sec.gov/Archives/edgar/data/1403161/000140316125000077/q42025earningsrelease.htm
A45: Current maturities of debt | B45: $mm | C45: 999 | D45: 2250 | E45: 0 | F45: 0 | G45: 5569 | H45: 5-yr XBRL extract of 10-K filings (edgar.tools): https://app.edgar.tools/companies/V · FY24–25 also Q4 FY2025 earnings release (8-K Ex. 99.1): https://www.sec.gov/Archives/edgar/data/1403161/000140316125000077/q42025earningsrelease.htm
A46: Long-term debt | B46: $mm | C46: 19978 | D46: 20200 | E46: 20463 | F46: 20836 | G46: 19602 | H46: 5-yr XBRL extract of 10-K filings (edgar.tools): https://app.edgar.tools/companies/V · FY24–25 also Q4 FY2025 earnings release (8-K Ex. 99.1): https://www.sec.gov/Archives/edgar/data/1403161/000140316125000077/q42025earningsrelease.htm
A47: Accrued litigation | B47: $mm | C47: 983 | D47: 1456 | E47: 1751 | F47: 1727 | G47: 3033 | H47: 5-yr XBRL extract of 10-K filings (edgar.tools): https://app.edgar.tools/companies/V · FY24–25 also Q4 FY2025 earnings release (8-K Ex. 99.1): https://www.sec.gov/Archives/edgar/data/1403161/000140316125000077/q42025earningsrelease.htm
A48: Total equity | B48: $mm | C48: 37589 | D48: 35581 | E48: 38733 | F48: 39137 | G48: 37909 | H48: 5-yr XBRL extract of 10-K filings (edgar.tools): https://app.edgar.tools/companies/V · FY24–25 also Q4 FY2025 earnings release (8-K Ex. 99.1): https://www.sec.gov/Archives/edgar/data/1403161/000140316125000077/q42025earningsrelease.htm
A49: Total assets | B49: $mm | C49: 82896 | D49: 85501 | E49: 90499 | F49: 94511 | G49: 99627 | H49: 5-yr XBRL extract of 10-K filings (edgar.tools): https://app.edgar.tools/companies/V · FY24–25 also Q4 FY2025 earnings release (8-K Ex. 99.1): https://www.sec.gov/Archives/edgar/data/1403161/000140316125000077/q42025earningsrelease.htm
A51: Cash flow & capital returns ($ millions)
A52: Net cash from operating activities | B52: $mm | C52: 15227 | D52: 18849 | E52: 20755 | F52: 19950 | G52: 23059 | H52: 5-yr XBRL extract of 10-K filings (edgar.tools): https://app.edgar.tools/companies/V
A53: Less: Purchases of property, equipment & technology | B53: $mm | C53: 705 | D53: 970 | E53: 1059 | F53: 1257 | G53: 1482 | H53: 5-yr XBRL extract of 10-K filings (edgar.tools): https://app.edgar.tools/companies/V
A54: Less: Repurchases of class A common stock | B54: $mm | C54: 8676 | D54: 11589 | E54: 12101 | F54: 16713 | G54: 18316 | H54: FY21–22: Visa FY2022 Form 10-K: https://www.sec.gov/Archives/edgar/data/1403161/000140316122000081/v-20220930.htm · FY23–25: 5-yr XBRL extract of 10-K filings (edgar.tools): https://app.edgar.tools/companies/V
A55: Less: Dividends paid | B55: $mm | C55: 2798 | D55: 3203 | E55: 3751 | F55: 4217 | G55: 4634 | H55: FY21–22: Visa FY2022 Form 10-K: https://www.sec.gov/Archives/edgar/data/1403161/000140316122000081/v-20220930.htm · FY23–25: 5-yr XBRL extract of 10-K filings (edgar.tools): https://app.edgar.tools/companies/V
A57: Integrity checks (should all be 0)
A58: Revenue components − client incentives − net revenue | C58: =C12+C13+C14+C15-C16-C17 -> 0 | D58: =D12+D13+D14+D15-D16-D17 -> 0 | E58: =E12+E13+E14+E15-E16-E17 -> 0 | F58: =F12+F13+F14+F15-F16-F17 -> 0 | G58: =G12+G13+G14+G15-G16-G17 -> 0
A59: Opex lines − total opex | C59: =SUM(C20:C26)-C27 -> 0 | D59: =SUM(D20:D26)-D27 -> 0 | E59: =SUM(E20:E26)-E27 -> 0 | F59: =SUM(F20:F26)-F27 -> 0 | G59: =SUM(G20:G26)-G27 -> 0
A60: Net revenue − opex − operating income | C60: =C17-C27-C31 -> 0 | D60: =D17-D27-D31 -> 0 | E60: =E17-E27-E31 -> 0 | F60: =F17-F27-F31 -> 0 | G60: =G17-G27-G31 -> 0
A61: Operating income + non-op − pre-tax income | C61: =C31+C33-C34 -> 0 | D61: =D31+D33-D34 -> 0 | E61: =E31+E33-E34 -> 0 | F61: =F31+F33-F34 -> 0 | G61: =G31+G33-G34 -> 0
A62: Pre-tax income − tax − net income | C62: =C34-C35-C36 -> 0 | D62: =D34-D35-D36 -> 0 | E62: =E34-E35-E36 -> 0 | F62: =F34-F35-F36 -> 0 | G62: =G34-G35-G36 -> 0
A63: Total errors (sum of absolute differences) | C63: =SUMPRODUCT(ABS(C58:G62)) -> 0
A66: Footnotes
A67: 1. Payments volume is reported for the 12 months ended Sep 30, matching the fiscal year. The timing lag sits in revenue: Visa recognises service revenue on the PRIOR quarter's payments volume, so the take rate (net revenue ÷ payments volume) mixes ~one quarter of offset. Disclose in Tab 1.
A68: 2. Litigation: most of the provision relates to U.S. covered litigation, funded via the escrow under the retrospective responsibility plan — deposits reduce the class B→A conversion rate, so legacy class B holders bear much of the cost. Basis for the 'EBIT ex-litigation' row in Tab 2.
A69: 3. FY25 debt rose because of new issuance; $5,569M is current (due within 12 months).
A70: 4. Values are as reported in each year's latest filing; no restatements applied. FY22 revenue components use the FY24 10-K presentation.
A74: Market data at fiscal year-end
A75: Share price at FY-end close (unadjusted) | B75: $ / share | C75: 222.75 | D75: 177.65 | E75: 230.01 | F75: 274.95 | G75: 341.38 | H75: Yahoo Finance daily history, Close column (unadjusted), all five years verified Oct 15, 2026: Sep 30 2021 · Sep 30 2022 · Sep 29 2023 (Sep 30 was a Saturday) · Sep 30 2024 · Sep 30 2025 — https://finance.yahoo.com/quote/V/history/
A76: As-converted class A shares outstanding at FY-end | B76: millions | C76: 2161 | D76: 2103 | E76: 2047 | F76: 1983 | G76: 1930 | H76: 10-K Stockholders' Equity note, as-converted table (all classes and preferred series): FY21–22 FY22 10-K R91 https://www.sec.gov/Archives/edgar/data/1403161/000140316122000081/R91.htm · FY23–24 FY24 10-K R83 https://www.sec.gov/Archives/edgar/data/1403161/000140316124000058/R83.htm · FY25 FY25 10-K R84 https://www.sec.gov/Archives/edgar/data/1403161/000140316125000089/R84.htm
A77: Quarterly dividend rate declared during the fiscal year | B77: $ / share | C77: 0.32 | D77: 0.375 | E77: 0.45 | F77: 0.52 | G77: 0.59 | H77: FY21 $0.32: FY21 10-K equity note · FY22 $0.375: declared Oct 22, 2021 (FY21 10-K) · FY23 $0.45: declared Oct 21, 2022 (FY22 10-K) · FY24 $0.52: Oct 2023 (FY23 10-K R85) · FY25 $0.59: Oct 2024 (FY24 10-K R84) · FY26 rate is $0.67 (FY25 10-K R85)

Sheet Data_MA
A1: Mastercard Inc. (NYSE: MA) — Peer Database, FY21–FY25
A2: $ in millions unless noted · Mastercard's fiscal year ends DECEMBER 31 (Visa: September 30) — FY25 = calendar 2025, a 3-month offset
A3: Legend: blue = hardcoded from filings · black = formula · yellow = placeholder / verify · outflows stored as positive amounts
A5: Line item | B5: Unit | C5: FY21 | D5: FY22 | E5: FY23 | F5: FY24 | G5: FY25 | H5: Source
A7: Operational volume
A8: Gross dollar volume (GDV) | B8: $ billions | C8: 7725 | D8: 8180 | E8: 9030 | F8: 9780 | G8: 10632 | H8: FY21: 4Q22 release: https://s25.q4cdn.com/479285134/files/doc_financials/2022/q4/4Q22-Mastercard-Earnings-Release.pdf · FY22–23: 4Q23 release: https://s25.q4cdn.com/479285134/files/doc_financials/2023/q4/4Q23-Mastercard-Earnings-Release.pdf (FY22 restated 8,177→8,180) · FY24–25: Mastercard 4Q25 earnings release: https://s25.q4cdn.com/479285134/files/doc_financials/2025/q4/4Q25-Mastercard-Earnings-Release.pdf
A9: Purchase volume (excl. cash — comparable to Visa payments volume) | B9: $ billions | C9: 5974 | D9: 6571 | E9: 7345 | F9: 8003 | G9: 8799 | H9: Same sources as GDV
A11: Income statement
A12: Net revenue | B12: $mm | C12: 18884 | D12: 22237 | E12: 25098 | F12: 28167 | G12: 32791 | H12: Mastercard FY2025 10-K / 5-yr XBRL extract (edgar.tools): https://app.edgar.tools/companies/MA
A13: Total operating expenses | B13: $mm | C13: 8802 | D13: 9973 | E13: 11090 | F13: 12585 | G13: 13894 | H13: Mastercard FY2025 10-K / 5-yr XBRL extract (edgar.tools): https://app.edgar.tools/companies/MA
A14: Provision for litigation | B14: $mm | C14: 94 | D14: 356 | E14: 539 | F14: 680 | G14: 504 | H14: Mastercard FY2025 10-K / 5-yr XBRL extract (edgar.tools): https://app.edgar.tools/companies/MA · FY24–25 confirmed in Mastercard 4Q25 earnings release: https://s25.q4cdn.com/479285134/files/doc_financials/2025/q4/4Q25-Mastercard-Earnings-Release.pdf
A15: Operating income | B15: $mm | C15: 10082 | D15: 12264 | E15: 14008 | F15: 15582 | G15: 18897 | H15: Mastercard FY2025 10-K / 5-yr XBRL extract (edgar.tools): https://app.edgar.tools/companies/MA
A16: Income tax expense | B16: $mm | C16: 1620 | D16: 1802 | E16: 2444 | F16: 2380 | G16: 3610 | H16: Mastercard FY2025 10-K / 5-yr XBRL extract (edgar.tools): https://app.edgar.tools/companies/MA
A17: Net income | B17: $mm | C17: 8687 | D17: 9930 | E17: 11195 | F17: 12874 | G17: 14968 | H17: Mastercard FY2025 10-K / 5-yr XBRL extract (edgar.tools): https://app.edgar.tools/companies/MA
A18: Income before income taxes | B18: $mm | C18: =C17+C16 -> 10307 | D18: 11732 | E18: 13639 | F18: 15254 | G18: 18578 | H18: Mastercard FY2025 10-K / 5-yr XBRL extract (edgar.tools): https://app.edgar.tools/companies/MA · FY21 not shown in extract: = net income + tax
A20: Balance sheet at Dec 31
A21: Cash and cash equivalents | B21: $mm | C21: 7421 | D21: 7008 | E21: 8588 | F21: 8442 | G21: 10566 | H21: Mastercard FY2025 10-K / 5-yr XBRL extract (edgar.tools): https://app.edgar.tools/companies/MA
A22: Restricted cash (mainly litigation settlement) — not deducted | B22: $mm | C22: 586 | D22: 589 | E22: 32 | F22: 492 | G22: 561 | H22: Mastercard FY2025 10-K / 5-yr XBRL extract (edgar.tools): https://app.edgar.tools/companies/MA
A23: Investments | B23: $mm | C23: 473 | D23: 400 | E23: 592 | F23: 330 | G23: 332 | H23: Mastercard FY2025 10-K / 5-yr XBRL extract (edgar.tools): https://app.edgar.tools/companies/MA
A24: Goodwill | B24: $mm | C24: 7662 | D24: 7522 | E24: 7660 | F24: 9193 | G24: 9560 | H24: Mastercard FY2025 10-K / 5-yr XBRL extract (edgar.tools): https://app.edgar.tools/companies/MA
A25: Other intangible assets, net | B25: $mm | C25: 3671 | D25: 3859 | E25: 4086 | F25: 5453 | G25: 5554 | H25: Mastercard FY2025 10-K / 5-yr XBRL extract (edgar.tools): https://app.edgar.tools/companies/MA
A26: Short-term debt | B26: $mm | C26: 792 | D26: 274 | E26: 1337 | F26: 750 | G26: 749 | H26: Mastercard FY2025 10-K / 5-yr XBRL extract (edgar.tools): https://app.edgar.tools/companies/MA
A27: Long-term debt | B27: $mm | C27: 13109 | D27: 13749 | E27: 14344 | F27: 17476 | G27: 18251 | H27: Mastercard FY2025 10-K / 5-yr XBRL extract (edgar.tools): https://app.edgar.tools/companies/MA
A28: Total equity (incl. non-controlling interests) | B28: $mm | C28: 7383 | D28: 6356 | E28: 6975 | F28: 6515 | G28: 7746 | H28: Mastercard FY2025 10-K / 5-yr XBRL extract (edgar.tools): https://app.edgar.tools/companies/MA
A30: Cash flow
A31: Net cash from operating activities | B31: $mm | C31: 9463 | D31: 11195 | E31: 11980 | F31: 14780 | G31: 17648 | H31: Mastercard FY2025 10-K / 5-yr XBRL extract (edgar.tools): https://app.edgar.tools/companies/MA
A32: Less: Purchases of property and equipment | B32: $mm | C32: 407 | D32: 442 | E32: 371 | F32: 474 | G32: 489 | H32: Mastercard FY2025 10-K / 5-yr XBRL extract (edgar.tools): https://app.edgar.tools/companies/MA
A33: Less: Capitalized software | B33: $mm | C33: 407 | D33: 655 | E33: 717 | F33: 720 | G33: 726 | H33: Mastercard FY2025 10-K / 5-yr XBRL extract (edgar.tools): https://app.edgar.tools/companies/MA
A34: Acquisitions, net of cash acquired | B34: $mm | C34: 4436 | D34: 313 | E34: 0 | F34: 2511 | G34: 0 | H34: Mastercard FY2025 10-K / 5-yr XBRL extract (edgar.tools): https://app.edgar.tools/companies/MA
A35: Less: Purchases of treasury stock (buybacks) | B35: $mm | C35: 5904 | D35: 8753 | E35: 9032 | F35: 10954 | G35: 11727 | H35: Mastercard FY2025 10-K / 5-yr XBRL extract (edgar.tools): https://app.edgar.tools/companies/MA
A36: Less: Dividends paid | B36: $mm | C36: 1741 | D36: 1903 | E36: 2158 | F36: 2448 | G36: 2756 | H36: Mastercard FY2025 10-K / 5-yr XBRL extract (edgar.tools): https://app.edgar.tools/companies/MA
A38: Market data (current)
A39: Class A + Class B shares outstanding (millions) | B39: millions | G39: 876 | H39: Mastercard Q2 2026 Form 10-Q: https://www.sec.gov/Archives/edgar/data/0001141391/000114139126000083/ma-20260630.htm — cover page Jul 27, 2026: Class A 869.46M + Class B 6.55M
A40: Share price ($) | B40: $ / share | G40: 603.24 | H40: Oct 14, 2026 close, as supplied (Yahoo Finance) — consistent with your Oct 15 screenshot ($618.94, +2.60% → prior close ≈ $603.2). Same valuation date as Visa
A41: Raw beta (5-year monthly) | B41: x | G41: 0.76 | H41: Yahoo Finance 'Beta (5Y Monthly)' 0.76, as supplied — third-party, like Visa's
A42: Total debt (Jun 30, 2026) | B42: $mm | G42: 24643 | H42: Mastercard Q2 2026 Form 10-Q: https://www.sec.gov/Archives/edgar/data/0001141391/000114139126000083/ma-20260630.htm — short-term $2,459M + long-term $22,184M
A44: Check: net revenue – opex – operating income (should be 0) | C44: =C12-C13-C15 -> 0 | D44: =D12-D13-D15 -> 0 | E44: =E12-E13-E15 -> 0 | F44: =F12-F13-F15 -> 0 | G44: =G12-G13-G15 -> 0
